{
  "strong_number": "H6979",
  "lemma": "קוּר",
  "pronunciation": "koor",
  "transliteration": "qûwr",
  "definitions": [
    {
      "text": "bore",
      "source": "bdb",
      "order": 1,
      "sense": "0"
    },
    {
      "text": "dig",
      "source": "bdb",
      "order": 2,
      "sense": "0"
    }
  ],
  "is_root": true,
  "occurrences": {
    "total": 5,
    "references": [
      "2kgs.19.24",
      "isa.22.5",
      "isa.37.25",
      "jer.6.7",
      "num.24.17"
    ]
  },
  "sources": {
    "strongs": false,
    "bdb": true
  }
}