{
  "reference": "psalms.105.36",
  "book_id": "psalms",
  "chapter": 105,
  "verse": 36,
  "hebrew_text": "וַ יַּ֣ךְ כָּל בְּכ֣וֹר בְּ אַרְצָ֑ ם רֵ֝אשִׁ֗ית לְ כָל אוֹנָֽ ם",
  "words": [
    {
      "position": 1,
      "hebrew": "וַיַּ֣ךְ",
      "strong_number": "H5221",
      "sense": null
    },
    {
      "position": 2,
      "hebrew": "כָּל",
      "strong_number": "H3605",
      "sense": null
    },
    {
      "position": 3,
      "hebrew": "בְּכ֣וֹר",
      "strong_number": "H1060",
      "sense": null
    },
    {
      "position": 4,
      "hebrew": "בְּאַרְצָ֑ם",
      "strong_number": "H776",
      "sense": "1"
    },
    {
      "position": 5,
      "hebrew": "רֵ֝אשִׁ֗ית",
      "strong_number": "H7225",
      "sense": "0"
    },
    {
      "position": 6,
      "hebrew": "לְכָל",
      "strong_number": "H3605",
      "sense": null
    },
    {
      "position": 7,
      "hebrew": "אוֹנָֽם",
      "strong_number": "H202",
      "sense": "0"
    }
  ]
}