{
  "reference": "judges.7.13",
  "book_id": "judges",
  "chapter": 7,
  "verse": 13,
  "hebrew_text": "וַ יָּבֹ֣א גִדְע֔וֹן וְ הִ֨נֵּה אִ֔ישׁ מְסַפֵּ֥ר לְ רֵעֵ֖ הוּ חֲל֑וֹם וַ יֹּ֜אמֶר הִנֵּ֧ה חֲל֣וֹם חָלַ֗מְתִּי וְ הִנֵּ֨ה צלול צְלִ֜יל לֶ֤חֶם שְׂעֹרִים֙ מִתְהַפֵּךְ֙ בְּ מַחֲנֵ֣ה מִדְיָ֔ן וַ יָּבֹ֣א עַד הָ֠ אֹהֶל וַ יַּכֵּ֧ הוּ וַ יִּפֹּ֛ל וַ יַּהַפְכֵ֥ הוּ לְ מַ֖עְלָ ה וְ נָפַ֥ל הָ אֹֽהֶל",
  "words": [
    {
      "position": 1,
      "hebrew": "וַיָּבֹ֣א",
      "strong_number": "H935",
      "sense": null
    },
    {
      "position": 2,
      "hebrew": "גִדְע֔וֹן",
      "strong_number": "H1439",
      "sense": null
    },
    {
      "position": 3,
      "hebrew": "וְהִ֨נֵּה",
      "strong_number": "H2009",
      "sense": null
    },
    {
      "position": 4,
      "hebrew": "אִ֔ישׁ",
      "strong_number": "H376",
      "sense": null
    },
    {
      "position": 5,
      "hebrew": "מְסַפֵּ֥ר",
      "strong_number": "H5608",
      "sense": null
    },
    {
      "position": 6,
      "hebrew": "לְרֵעֵ֖הוּ",
      "strong_number": "H7453",
      "sense": null
    },
    {
      "position": 7,
      "hebrew": "חֲל֑וֹם",
      "strong_number": "H2472",
      "sense": "1"
    },
    {
      "position": 8,
      "hebrew": "וַיֹּ֜אמֶר",
      "strong_number": "H559",
      "sense": "0"
    },
    {
      "position": 9,
      "hebrew": "הִנֵּ֧ה",
      "strong_number": "H2009",
      "sense": null
    },
    {
      "position": 10,
      "hebrew": "חֲל֣וֹם",
      "strong_number": "H2472",
      "sense": null
    },
    {
      "position": 11,
      "hebrew": "חָלַ֗מְתִּי",
      "strong_number": "H2492",
      "sense": "0"
    },
    {
      "position": 12,
      "hebrew": "וְהִנֵּ֨ה",
      "strong_number": "H2009",
      "sense": null
    },
    {
      "position": 13,
      "hebrew": "צלול",
      "strong_number": "H6742",
      "sense": null
    },
    {
      "position": 14,
      "hebrew": "צְלִ֜יל",
      "strong_number": "H6742",
      "sense": "0"
    },
    {
      "position": 15,
      "hebrew": "לֶ֤חֶם",
      "strong_number": "H3899",
      "sense": null
    },
    {
      "position": 16,
      "hebrew": "שְׂעֹרִים֙",
      "strong_number": "H8184",
      "sense": "0"
    },
    {
      "position": 17,
      "hebrew": "מִתְהַפֵּךְ֙",
      "strong_number": "H2015",
      "sense": "0"
    },
    {
      "position": 18,
      "hebrew": "בְּמַחֲנֵ֣ה",
      "strong_number": "H4264",
      "sense": null
    },
    {
      "position": 19,
      "hebrew": "מִדְיָ֔ן",
      "strong_number": "H4080",
      "sense": null
    },
    {
      "position": 20,
      "hebrew": "וַיָּבֹ֣א",
      "strong_number": "H935",
      "sense": null
    },
    {
      "position": 21,
      "hebrew": "עַד",
      "strong_number": "H5704",
      "sense": null
    },
    {
      "position": 22,
      "hebrew": "הָ֠אֹהֶל",
      "strong_number": "H168",
      "sense": "0"
    },
    {
      "position": 23,
      "hebrew": "וַיַּכֵּ֧הוּ",
      "strong_number": "H5221",
      "sense": null
    },
    {
      "position": 24,
      "hebrew": "וַיִּפֹּ֛ל",
      "strong_number": "H5307",
      "sense": "0"
    },
    {
      "position": 25,
      "hebrew": "וַיַּהַפְכֵ֥הוּ",
      "strong_number": "H2015",
      "sense": null
    },
    {
      "position": 26,
      "hebrew": "לְמַ֖עְלָה",
      "strong_number": "H4605",
      "sense": "0"
    },
    {
      "position": 27,
      "hebrew": "וְנָפַ֥ל",
      "strong_number": "H5307",
      "sense": null
    },
    {
      "position": 28,
      "hebrew": "הָאֹֽהֶל",
      "strong_number": "H168",
      "sense": "0"
    }
  ]
}