{
  "reference": "judges.11.9",
  "book_id": "judges",
  "chapter": 11,
  "verse": 9,
  "hebrew_text": "וַ יֹּ֨אמֶר יִפְתָּ֜ח אֶל זִקְנֵ֣י גִלְעָ֗ד אִם מְשִׁיבִ֨ים אַתֶּ֤ם אוֹתִ י֙ לְ הִלָּחֵם֙ בִּ בְנֵ֣י עַמּ֔וֹן וְ נָתַ֧ן יְהוָ֛ה אוֹתָ֖ ם לְ פָנָ֑ י אָנֹכִ֕י אֶהְיֶ֥ה לָ כֶ֖ם לְ רֹֽאשׁ",
  "words": [
    {
      "position": 1,
      "hebrew": "וַיֹּ֨אמֶר",
      "strong_number": "H559",
      "sense": null
    },
    {
      "position": 2,
      "hebrew": "יִפְתָּ֜ח",
      "strong_number": "H3316",
      "sense": "1"
    },
    {
      "position": 3,
      "hebrew": "אֶל",
      "strong_number": "H413",
      "sense": null
    },
    {
      "position": 4,
      "hebrew": "זִקְנֵ֣י",
      "strong_number": "H2205",
      "sense": null
    },
    {
      "position": 5,
      "hebrew": "גִלְעָ֗ד",
      "strong_number": "H1568",
      "sense": null
    },
    {
      "position": 6,
      "hebrew": "אִם",
      "strong_number": "H518",
      "sense": null
    },
    {
      "position": 7,
      "hebrew": "מְשִׁיבִ֨ים",
      "strong_number": "H7725",
      "sense": null
    },
    {
      "position": 8,
      "hebrew": "אַתֶּ֤ם",
      "strong_number": "H859",
      "sense": null
    },
    {
      "position": 9,
      "hebrew": "אוֹתִי֙",
      "strong_number": "H853",
      "sense": "1"
    },
    {
      "position": 10,
      "hebrew": "לְהִלָּחֵם֙",
      "strong_number": "H3898",
      "sense": null
    },
    {
      "position": 11,
      "hebrew": "בִּבְנֵ֣י",
      "strong_number": "H1121",
      "sense": null
    },
    {
      "position": 12,
      "hebrew": "עַמּ֔וֹן",
      "strong_number": "H5983",
      "sense": null
    },
    {
      "position": 13,
      "hebrew": "וְנָתַ֧ן",
      "strong_number": "H5414",
      "sense": null
    },
    {
      "position": 14,
      "hebrew": "יְהוָ֛ה",
      "strong_number": "H3068",
      "sense": null
    },
    {
      "position": 15,
      "hebrew": "אוֹתָ֖ם",
      "strong_number": "H853",
      "sense": "1"
    },
    {
      "position": 16,
      "hebrew": "לְפָנָ֑י",
      "strong_number": "H6440",
      "sense": null
    },
    {
      "position": 17,
      "hebrew": "אָנֹכִ֕י",
      "strong_number": "H595",
      "sense": null
    },
    {
      "position": 18,
      "hebrew": "אֶהְיֶ֥ה",
      "strong_number": "H1961",
      "sense": null
    },
    {
      "position": 19,
      "hebrew": "לָכֶ֖ם",
      "strong_number": "H3808",
      "sense": null
    },
    {
      "position": 20,
      "hebrew": "לְרֹֽאשׁ",
      "strong_number": "H7218",
      "sense": "0"
    }
  ]
}