{
  "reference": "judges.10.17",
  "book_id": "judges",
  "chapter": 10,
  "verse": 17,
  "hebrew_text": "וַ יִּצָּֽעֲקוּ֙ בְּנֵ֣י עַמּ֔וֹן וַֽ יַּחֲנ֖וּ בַּ גִּלְעָ֑ד וַ יֵּאָֽסְפוּ֙ בְּנֵ֣י יִשְׂרָאֵ֔ל וַֽ יַּחֲנ֖וּ בַּ מִּצְפָּֽה",
  "words": [
    {
      "position": 1,
      "hebrew": "וַיִּצָּֽעֲקוּ֙",
      "strong_number": "H6817",
      "sense": null
    },
    {
      "position": 2,
      "hebrew": "בְּנֵ֣י",
      "strong_number": "H1121",
      "sense": null
    },
    {
      "position": 3,
      "hebrew": "עַמּ֔וֹן",
      "strong_number": "H5983",
      "sense": null
    },
    {
      "position": 4,
      "hebrew": "וַֽיַּחֲנ֖וּ",
      "strong_number": "H2583",
      "sense": "1"
    },
    {
      "position": 5,
      "hebrew": "בַּגִּלְעָ֑ד",
      "strong_number": "H1568",
      "sense": null
    },
    {
      "position": 6,
      "hebrew": "וַיֵּאָֽסְפוּ֙",
      "strong_number": "H622",
      "sense": null
    },
    {
      "position": 7,
      "hebrew": "בְּנֵ֣י",
      "strong_number": "H1121",
      "sense": null
    },
    {
      "position": 8,
      "hebrew": "יִשְׂרָאֵ֔ל",
      "strong_number": "H3478",
      "sense": "0"
    },
    {
      "position": 9,
      "hebrew": "וַֽיַּחֲנ֖וּ",
      "strong_number": "H2583",
      "sense": "0"
    },
    {
      "position": 10,
      "hebrew": "בַּמִּצְפָּֽה",
      "strong_number": "H4709",
      "sense": null
    }
  ]
}