{
  "reference": "genesis.22.1",
  "book_id": "genesis",
  "chapter": 22,
  "verse": 1,
  "hebrew_text": "וַ יְהִ֗י אַחַר֙ הַ דְּבָרִ֣ים הָ אֵ֔לֶּה וְ הָ֣ אֱלֹהִ֔ים נִסָּ֖ה אֶת אַבְרָהָ֑ם וַ יֹּ֣אמֶר אֵלָ֔י ו אַבְרָהָ֖ם וַ יֹּ֥אמֶר הִנֵּֽנִ י",
  "words": [
    {
      "position": 1,
      "hebrew": "וַיְהִ֗י",
      "strong_number": "H1961",
      "sense": "1"
    },
    {
      "position": 2,
      "hebrew": "אַחַר֙",
      "strong_number": "H310",
      "sense": "1"
    },
    {
      "position": 3,
      "hebrew": "הַדְּבָרִ֣ים",
      "strong_number": "H1697",
      "sense": null
    },
    {
      "position": 4,
      "hebrew": "הָאֵ֔לֶּה",
      "strong_number": "H428",
      "sense": "1"
    },
    {
      "position": 5,
      "hebrew": "וְהָ֣אֱלֹהִ֔ים",
      "strong_number": "H430",
      "sense": "1"
    },
    {
      "position": 6,
      "hebrew": "נִסָּ֖ה",
      "strong_number": "H5254",
      "sense": null
    },
    {
      "position": 7,
      "hebrew": "אֶת",
      "strong_number": "H853",
      "sense": null
    },
    {
      "position": 8,
      "hebrew": "אַבְרָהָ֑ם",
      "strong_number": "H85",
      "sense": null
    },
    {
      "position": 9,
      "hebrew": "וַיֹּ֣אמֶר",
      "strong_number": "H559",
      "sense": null
    },
    {
      "position": 10,
      "hebrew": "אֵלָ֔יו",
      "strong_number": "H413",
      "sense": "0"
    },
    {
      "position": 11,
      "hebrew": "אַבְרָהָ֖ם",
      "strong_number": "H85",
      "sense": "0"
    },
    {
      "position": 12,
      "hebrew": "וַיֹּ֥אמֶר",
      "strong_number": "H559",
      "sense": null
    },
    {
      "position": 13,
      "hebrew": "הִנֵּֽנִי",
      "strong_number": "H2009",
      "sense": "0"
    }
  ]
}