{
  "reference": "jeremiah.12.9",
  "book_id": "jeremiah",
  "chapter": 12,
  "verse": 9,
  "hebrew_text": "הַ עַ֨יִט צָב֤וּעַ נַחֲלָתִ י֙ לִ֔ י הַ עַ֖יִט סָבִ֣יב עָלֶ֑י הָ לְכ֗וּ אִסְפ֛וּ כָּל חַיַּ֥ת הַ שָּׂדֶ֖ה הֵתָ֥יוּ לְ אָכְלָֽה",
  "words": [
    {
      "position": 1,
      "hebrew": "הַעַ֨יִט",
      "strong_number": "H5861",
      "sense": null
    },
    {
      "position": 2,
      "hebrew": "צָב֤וּעַ",
      "strong_number": "H6641",
      "sense": null
    },
    {
      "position": 3,
      "hebrew": "נַחֲלָתִי֙",
      "strong_number": "H5159",
      "sense": "1"
    },
    {
      "position": 4,
      "hebrew": "לִ֔י",
      "strong_number": "H3808",
      "sense": null
    },
    {
      "position": 5,
      "hebrew": "הַעַ֖יִט",
      "strong_number": "H5861",
      "sense": null
    },
    {
      "position": 6,
      "hebrew": "סָבִ֣יב",
      "strong_number": "H5439",
      "sense": null
    },
    {
      "position": 7,
      "hebrew": "עָלֶ֑יהָ",
      "strong_number": "H5921",
      "sense": null
    },
    {
      "position": 8,
      "hebrew": "לְכ֗וּ",
      "strong_number": "H3212",
      "sense": null
    },
    {
      "position": 9,
      "hebrew": "אִסְפ֛וּ",
      "strong_number": "H622",
      "sense": null
    },
    {
      "position": 10,
      "hebrew": "כָּל",
      "strong_number": "H3605",
      "sense": null
    },
    {
      "position": 11,
      "hebrew": "חַיַּ֥ת",
      "strong_number": "H2416",
      "sense": null
    },
    {
      "position": 12,
      "hebrew": "הַשָּׂדֶ֖ה",
      "strong_number": "H7704",
      "sense": null
    },
    {
      "position": 13,
      "hebrew": "הֵתָ֥יוּ",
      "strong_number": "H857",
      "sense": null
    },
    {
      "position": 14,
      "hebrew": "לְאָכְלָֽה",
      "strong_number": "H402",
      "sense": "0"
    }
  ]
}