[
  {
    "chapter": 19,
    "verse": 1,
    "hebrew": "מַשָּׂ֖א מִצְרָ֑יִם הִנֵּ֨ה יְהוָ֜ה רֹכֵ֨ב עַל עָ֥ב קַל֙ וּ/בָ֣א מִצְרַ֔יִם וְ/נָע֞וּ אֱלִילֵ֤י מִצְרַ֨יִם֙ מִ/פָּנָ֔י/ו וּ/לְבַ֥ב מִצְרַ֖יִם יִמַּ֥ס בְּ/קִרְבּֽ/וֹ",
    "hebrew_no_nikud": "משא מצרים הנה יהוה רכב על עב קל ו/בא מצרים ו/נעו אלילי מצרים מ/פני/ו ו/לבב מצרים ימס ב/קרב/ו",
    "words": [
      {
        "text": "מַשָּׂ֖א",
        "text_no_nikud": "משא",
        "lemma": "H4853",
        "strong": "H4853",
        "morph": "HNcmsc"
      },
      {
        "text": "מִצְרָ֑יִם",
        "text_no_nikud": "מצרים",
        "lemma": "H4714",
        "strong": "H4714",
        "morph": "HNp"
      },
      {
        "text": "הִנֵּ֨ה",
        "text_no_nikud": "הנה",
        "lemma": "H2009",
        "strong": "H2009",
        "morph": "HTm"
      },
      {
        "text": "יְהוָ֜ה",
        "text_no_nikud": "יהוה",
        "lemma": "H3068",
        "strong": "H3068",
        "morph": "HNp"
      },
      {
        "text": "רֹכֵ֨ב",
        "text_no_nikud": "רכב",
        "lemma": "H7392",
        "strong": "H7392",
        "morph": "HVqrmsa"
      },
      {
        "text": "עַל",
        "text_no_nikud": "על",
        "lemma": "H5921",
        "strong": "H5921",
        "morph": "HR"
      },
      {
        "text": "עָ֥ב",
        "text_no_nikud": "עב",
        "lemma": "H5645",
        "strong": "H5645",
        "morph": "HNcbsa"
      },
      {
        "text": "קַל֙",
        "text_no_nikud": "קל",
        "lemma": "H7031",
        "strong": "H7031",
        "morph": "HAamsa"
      },
      {
        "text": "וּ/בָ֣א",
        "text_no_nikud": "ו/בא",
        "lemma": "Hc/H935",
        "strong": "Hc/H935",
        "morph": "HC/Vqrmsa"
      },
      {
        "text": "מִצְרַ֔יִם",
        "text_no_nikud": "מצרים",
        "lemma": "H4714",
        "strong": "H4714",
        "morph": "HNp"
      },
      {
        "text": "וְ/נָע֞וּ",
        "text_no_nikud": "ו/נעו",
        "lemma": "Hc/H5128",
        "strong": "Hc/H5128",
        "morph": "HC/Vqq3cp"
      },
      {
        "text": "אֱלִילֵ֤י",
        "text_no_nikud": "אלילי",
        "lemma": "H457",
        "strong": "H457",
        "morph": "HNcmpc"
      },
      {
        "text": "מִצְרַ֨יִם֙",
        "text_no_nikud": "מצרים",
        "lemma": "H4714",
        "strong": "H4714",
        "morph": "HNp"
      },
      {
        "text": "מִ/פָּנָ֔י/ו",
        "text_no_nikud": "מ/פני/ו",
        "lemma": "Hm/H6440",
        "strong": "Hm/H6440",
        "morph": "HR/Ncbpc/Sp3ms"
      },
      {
        "text": "וּ/לְבַ֥ב",
        "text_no_nikud": "ו/לבב",
        "lemma": "Hc/H3824",
        "strong": "Hc/H3824",
        "morph": "HC/Ncmsc"
      },
      {
        "text": "מִצְרַ֖יִם",
        "text_no_nikud": "מצרים",
        "lemma": "H4714",
        "strong": "H4714",
        "morph": "HNp"
      },
      {
        "text": "יִמַּ֥ס",
        "text_no_nikud": "ימס",
        "lemma": "H4549",
        "strong": "H4549",
        "morph": "HVNi3ms"
      },
      {
        "text": "בְּ/קִרְבּֽ/וֹ",
        "text_no_nikud": "ב/קרב/ו",
        "lemma": "Hb/H7130",
        "strong": "Hb/H7130",
        "morph": "HR/Ncmsc/Sp3ms"
      }
    ]
  },
  {
    "chapter": 19,
    "verse": 2,
    "hebrew": "וְ/סִכְסַכְתִּ֤י מִצְרַ֨יִם֙ בְּ/מִצְרַ֔יִם וְ/נִלְחֲמ֥וּ אִישׁ בְּ/אָחִ֖י/ו וְ/אִ֣ישׁ בְּ/רֵעֵ֑/הוּ עִ֣יר בְּ/עִ֔יר מַמְלָכָ֖ה בְּ/מַמְלָכָֽה",
    "hebrew_no_nikud": "ו/סכסכתי מצרים ב/מצרים ו/נלחמו איש ב/אחי/ו ו/איש ב/רע/הו עיר ב/עיר ממלכה ב/ממלכה",
    "words": [
      {
        "text": "וְ/סִכְסַכְתִּ֤י",
        "text_no_nikud": "ו/סכסכתי",
        "lemma": "Hc/H5526",
        "strong": "Hc/H5526",
        "morph": "HC/Vlq1cs"
      },
      {
        "text": "מִצְרַ֨יִם֙",
        "text_no_nikud": "מצרים",
        "lemma": "H4714",
        "strong": "H4714",
        "morph": "HNp"
      },
      {
        "text": "בְּ/מִצְרַ֔יִם",
        "text_no_nikud": "ב/מצרים",
        "lemma": "Hb/H4714",
        "strong": "Hb/H4714",
        "morph": "HR/Np"
      },
      {
        "text": "וְ/נִלְחֲמ֥וּ",
        "text_no_nikud": "ו/נלחמו",
        "lemma": "Hc/H3898",
        "strong": "Hc/H3898",
        "morph": "HC/VNq3cp"
      },
      {
        "text": "אִישׁ",
        "text_no_nikud": "איש",
        "lemma": "H376",
        "strong": "H376",
        "morph": "HNcmsa"
      },
      {
        "text": "בְּ/אָחִ֖י/ו",
        "text_no_nikud": "ב/אחי/ו",
        "lemma": "Hb/H251",
        "strong": "Hb/H251",
        "morph": "HR/Ncmsc/Sp3ms"
      },
      {
        "text": "וְ/אִ֣ישׁ",
        "text_no_nikud": "ו/איש",
        "lemma": "Hc/H376",
        "strong": "Hc/H376",
        "morph": "HC/Ncmsa"
      },
      {
        "text": "בְּ/רֵעֵ֑/הוּ",
        "text_no_nikud": "ב/רע/הו",
        "lemma": "Hb/H7453",
        "strong": "Hb/H7453",
        "morph": "HR/Ncmsc/Sp3ms"
      },
      {
        "text": "עִ֣יר",
        "text_no_nikud": "עיר",
        "lemma": "H5892",
        "strong": "H5892",
        "morph": "HNcfsa"
      },
      {
        "text": "בְּ/עִ֔יר",
        "text_no_nikud": "ב/עיר",
        "lemma": "Hb/H5892",
        "strong": "Hb/H5892",
        "morph": "HR/Ncfsa"
      },
      {
        "text": "מַמְלָכָ֖ה",
        "text_no_nikud": "ממלכה",
        "lemma": "H4467",
        "strong": "H4467",
        "morph": "HNcfsa"
      },
      {
        "text": "בְּ/מַמְלָכָֽה",
        "text_no_nikud": "ב/ממלכה",
        "lemma": "Hb/H4467",
        "strong": "Hb/H4467",
        "morph": "HR/Ncfsa"
      }
    ]
  },
  {
    "chapter": 19,
    "verse": 3,
    "hebrew": "וְ/נָבְקָ֤ה רֽוּחַ מִצְרַ֨יִם֙ בְּ/קִרְבּ֔/וֹ וַ/עֲצָת֖/וֹ אֲבַלֵּ֑עַ וְ/דָרְשׁ֤וּ אֶל הָֽ/אֱלִילִים֙ וְ/אֶל הָ֣/אִטִּ֔ים וְ/אֶל הָ/אֹב֖וֹת וְ/אֶל הַ/יִּדְּעֹנִֽים",
    "hebrew_no_nikud": "ו/נבקה רוח מצרים ב/קרב/ו ו/עצת/ו אבלע ו/דרשו אל ה/אלילים ו/אל ה/אטים ו/אל ה/אבות ו/אל ה/ידענים",
    "words": [
      {
        "text": "וְ/נָבְקָ֤ה",
        "text_no_nikud": "ו/נבקה",
        "lemma": "Hc/H1238",
        "strong": "Hc/H1238",
        "morph": "HC/VNq3fs"
      },
      {
        "text": "רֽוּחַ",
        "text_no_nikud": "רוח",
        "lemma": "H7307",
        "strong": "H7307",
        "morph": "HNcbsc"
      },
      {
        "text": "מִצְרַ֨יִם֙",
        "text_no_nikud": "מצרים",
        "lemma": "H4714",
        "strong": "H4714",
        "morph": "HNp"
      },
      {
        "text": "בְּ/קִרְבּ֔/וֹ",
        "text_no_nikud": "ב/קרב/ו",
        "lemma": "Hb/H7130",
        "strong": "Hb/H7130",
        "morph": "HR/Ncmsc/Sp3ms"
      },
      {
        "text": "וַ/עֲצָת֖/וֹ",
        "text_no_nikud": "ו/עצת/ו",
        "lemma": "Hc/H6098",
        "strong": "Hc/H6098",
        "morph": "HC/Ncfsc/Sp3ms"
      },
      {
        "text": "אֲבַלֵּ֑עַ",
        "text_no_nikud": "אבלע",
        "lemma": "H1104",
        "strong": "H1104",
        "morph": "HVpi1cs"
      },
      {
        "text": "וְ/דָרְשׁ֤וּ",
        "text_no_nikud": "ו/דרשו",
        "lemma": "Hc/H1875",
        "strong": "Hc/H1875",
        "morph": "HC/Vqq3cp"
      },
      {
        "text": "אֶל",
        "text_no_nikud": "אל",
        "lemma": "H413",
        "strong": "H413",
        "morph": "HR"
      },
      {
        "text": "הָֽ/אֱלִילִים֙",
        "text_no_nikud": "ה/אלילים",
        "lemma": "Hd/H457",
        "strong": "Hd/H457",
        "morph": "HTd/Ncmpa"
      },
      {
        "text": "וְ/אֶל",
        "text_no_nikud": "ו/אל",
        "lemma": "Hc/H413",
        "strong": "Hc/H413",
        "morph": "HC/R"
      },
      {
        "text": "הָ֣/אִטִּ֔ים",
        "text_no_nikud": "ה/אטים",
        "lemma": "Hd/H328",
        "strong": "Hd/H328",
        "morph": "HTd/Ncmpa"
      },
      {
        "text": "וְ/אֶל",
        "text_no_nikud": "ו/אל",
        "lemma": "Hc/H413",
        "strong": "Hc/H413",
        "morph": "HC/R"
      },
      {
        "text": "הָ/אֹב֖וֹת",
        "text_no_nikud": "ה/אבות",
        "lemma": "Hd/H178",
        "strong": "Hd/H178",
        "morph": "HTd/Ncmpa"
      },
      {
        "text": "וְ/אֶל",
        "text_no_nikud": "ו/אל",
        "lemma": "Hc/H413",
        "strong": "Hc/H413",
        "morph": "HC/R"
      },
      {
        "text": "הַ/יִּדְּעֹנִֽים",
        "text_no_nikud": "ה/ידענים",
        "lemma": "Hd/H3049",
        "strong": "Hd/H3049",
        "morph": "HTd/Ncmpa"
      }
    ]
  },
  {
    "chapter": 19,
    "verse": 4,
    "hebrew": "וְ/סִכַּרְתִּי֙ אֶת מִצְרַ֔יִם בְּ/יַ֖ד אֲדֹנִ֣ים קָשֶׁ֑ה וּ/מֶ֤לֶךְ עַז֙ יִמְשָׁל בָּ֔/ם נְאֻ֥ם הָ/אָד֖וֹן יְהוָ֥ה צְבָאֽוֹת",
    "hebrew_no_nikud": "ו/סכרתי את מצרים ב/יד אדנים קשה ו/מלך עז ימשל ב/ם נאם ה/אדון יהוה צבאות",
    "words": [
      {
        "text": "וְ/סִכַּרְתִּי֙",
        "text_no_nikud": "ו/סכרתי",
        "lemma": "Hc/H5534",
        "strong": "Hc/H5534",
        "morph": "HC/Vpq1cs"
      },
      {
        "text": "אֶת",
        "text_no_nikud": "את",
        "lemma": "H853",
        "strong": "H853",
        "morph": "HTo"
      },
      {
        "text": "מִצְרַ֔יִם",
        "text_no_nikud": "מצרים",
        "lemma": "H4714",
        "strong": "H4714",
        "morph": "HNp"
      },
      {
        "text": "בְּ/יַ֖ד",
        "text_no_nikud": "ב/יד",
        "lemma": "Hb/H3027",
        "strong": "Hb/H3027",
        "morph": "HR/Ncbsc"
      },
      {
        "text": "אֲדֹנִ֣ים",
        "text_no_nikud": "אדנים",
        "lemma": "H113",
        "strong": "H113",
        "morph": "HNcmpa"
      },
      {
        "text": "קָשֶׁ֑ה",
        "text_no_nikud": "קשה",
        "lemma": "H7186",
        "strong": "H7186",
        "morph": "HAamsa"
      },
      {
        "text": "וּ/מֶ֤לֶךְ",
        "text_no_nikud": "ו/מלך",
        "lemma": "Hc/H4428",
        "strong": "Hc/H4428",
        "morph": "HC/Ncmsa"
      },
      {
        "text": "עַז֙",
        "text_no_nikud": "עז",
        "lemma": "H5794",
        "strong": "H5794",
        "morph": "HAamsa"
      },
      {
        "text": "יִמְשָׁל",
        "text_no_nikud": "ימשל",
        "lemma": "H4910",
        "strong": "H4910",
        "morph": "HVqi3ms"
      },
      {
        "text": "בָּ֔/ם",
        "text_no_nikud": "ב/ם",
        "lemma": "Hb",
        "strong": "Hb",
        "morph": "HR/Sp3mp"
      },
      {
        "text": "נְאֻ֥ם",
        "text_no_nikud": "נאם",
        "lemma": "H5002",
        "strong": "H5002",
        "morph": "HNcmsc"
      },
      {
        "text": "הָ/אָד֖וֹן",
        "text_no_nikud": "ה/אדון",
        "lemma": "Hd/H113",
        "strong": "Hd/H113",
        "morph": "HTd/Ncmsa"
      },
      {
        "text": "יְהוָ֥ה",
        "text_no_nikud": "יהוה",
        "lemma": "H3068",
        "strong": "H3068",
        "morph": "HNp"
      },
      {
        "text": "צְבָאֽוֹת",
        "text_no_nikud": "צבאות",
        "lemma": "H6635",
        "strong": "H6635",
        "morph": "HNcbpa"
      }
    ]
  },
  {
    "chapter": 19,
    "verse": 5,
    "hebrew": "וְ/נִשְּׁתוּ מַ֖יִם מֵֽ/הַ/יָּ֑ם וְ/נָהָ֖ר יֶחֱרַ֥ב וְ/יָבֵֽשׁ",
    "hebrew_no_nikud": "ו/נשתו מים מ/ה/ים ו/נהר יחרב ו/יבש",
    "words": [
      {
        "text": "וְ/נִשְּׁתוּ",
        "text_no_nikud": "ו/נשתו",
        "lemma": "Hc/H3001",
        "strong": "Hc/H3001",
        "morph": "HC/VNq3cp"
      },
      {
        "text": "מַ֖יִם",
        "text_no_nikud": "מים",
        "lemma": "H4325",
        "strong": "H4325",
        "morph": "HNcmpa"
      },
      {
        "text": "מֵֽ/הַ/יָּ֑ם",
        "text_no_nikud": "מ/ה/ים",
        "lemma": "Hm/Hd/H3220",
        "strong": "Hm/Hd/H3220",
        "morph": "HR/Td/Ncmsa"
      },
      {
        "text": "וְ/נָהָ֖ר",
        "text_no_nikud": "ו/נהר",
        "lemma": "Hc/H5104",
        "strong": "Hc/H5104",
        "morph": "HC/Ncmsa"
      },
      {
        "text": "יֶחֱרַ֥ב",
        "text_no_nikud": "יחרב",
        "lemma": "H2717",
        "strong": "H2717",
        "morph": "HVqi3ms"
      },
      {
        "text": "וְ/יָבֵֽשׁ",
        "text_no_nikud": "ו/יבש",
        "lemma": "Hc/H5405",
        "strong": "Hc/H5405",
        "morph": "HC/Vqq3ms"
      }
    ]
  },
  {
    "chapter": 19,
    "verse": 6,
    "hebrew": "וְ/הֶאֶזְנִ֣יחוּ נְהָר֔וֹת דָּלֲל֥וּ וְ/חָרְב֖וּ יְאֹרֵ֣י מָצ֑וֹר קָנֶ֥ה וָ/ס֖וּף קָמֵֽלוּ",
    "hebrew_no_nikud": "ו/האזניחו נהרות דללו ו/חרבו יארי מצור קנה ו/סוף קמלו",
    "words": [
      {
        "text": "וְ/הֶאֶזְנִ֣יחוּ",
        "text_no_nikud": "ו/האזניחו",
        "lemma": "Hc/H2186",
        "strong": "Hc/H2186",
        "morph": "HC/Vhq3cp"
      },
      {
        "text": "נְהָר֔וֹת",
        "text_no_nikud": "נהרות",
        "lemma": "H5104",
        "strong": "H5104",
        "morph": "HNcmpa"
      },
      {
        "text": "דָּלֲל֥וּ",
        "text_no_nikud": "דללו",
        "lemma": "H1809",
        "strong": "H1809",
        "morph": "HVqp3cp"
      },
      {
        "text": "וְ/חָרְב֖וּ",
        "text_no_nikud": "ו/חרבו",
        "lemma": "Hc/H2717",
        "strong": "Hc/H2717",
        "morph": "HC/Vqq3cp"
      },
      {
        "text": "יְאֹרֵ֣י",
        "text_no_nikud": "יארי",
        "lemma": "H2975",
        "strong": "H2975",
        "morph": "HNcmpc"
      },
      {
        "text": "מָצ֑וֹר",
        "text_no_nikud": "מצור",
        "lemma": "H4693",
        "strong": "H4693",
        "morph": "HNp"
      },
      {
        "text": "קָנֶ֥ה",
        "text_no_nikud": "קנה",
        "lemma": "H7070",
        "strong": "H7070",
        "morph": "HNcmsa"
      },
      {
        "text": "וָ/ס֖וּף",
        "text_no_nikud": "ו/סוף",
        "lemma": "Hc/H5488",
        "strong": "Hc/H5488",
        "morph": "HC/Ncmsa"
      },
      {
        "text": "קָמֵֽלוּ",
        "text_no_nikud": "קמלו",
        "lemma": "H7060",
        "strong": "H7060",
        "morph": "HVqp3cp"
      }
    ]
  },
  {
    "chapter": 19,
    "verse": 7,
    "hebrew": "עָר֥וֹת עַל יְא֖וֹר עַל פִּ֣י יְא֑וֹר וְ/כֹל֙ מִזְרַ֣ע יְא֔וֹר יִיבַ֥שׁ נִדַּ֖ף וְ/אֵינֶֽ/נּוּ",
    "hebrew_no_nikud": "ערות על יאור על פי יאור ו/כל מזרע יאור ייבש נדף ו/אינ/נו",
    "words": [
      {
        "text": "עָר֥וֹת",
        "text_no_nikud": "ערות",
        "lemma": "H6169",
        "strong": "H6169",
        "morph": "HNcfpa"
      },
      {
        "text": "עַל",
        "text_no_nikud": "על",
        "lemma": "H5921",
        "strong": "H5921",
        "morph": "HR"
      },
      {
        "text": "יְא֖וֹר",
        "text_no_nikud": "יאור",
        "lemma": "H2975",
        "strong": "H2975",
        "morph": "HNp"
      },
      {
        "text": "עַל",
        "text_no_nikud": "על",
        "lemma": "H5921",
        "strong": "H5921",
        "morph": "HR"
      },
      {
        "text": "פִּ֣י",
        "text_no_nikud": "פי",
        "lemma": "H6310",
        "strong": "H6310",
        "morph": "HNcmsc"
      },
      {
        "text": "יְא֑וֹר",
        "text_no_nikud": "יאור",
        "lemma": "H2975",
        "strong": "H2975",
        "morph": "HNp"
      },
      {
        "text": "וְ/כֹל֙",
        "text_no_nikud": "ו/כל",
        "lemma": "Hc/H3605",
        "strong": "Hc/H3605",
        "morph": "HC/Ncmsc"
      },
      {
        "text": "מִזְרַ֣ע",
        "text_no_nikud": "מזרע",
        "lemma": "H4218",
        "strong": "H4218",
        "morph": "HNcmsc"
      },
      {
        "text": "יְא֔וֹר",
        "text_no_nikud": "יאור",
        "lemma": "H2975",
        "strong": "H2975",
        "morph": "HNp"
      },
      {
        "text": "יִיבַ֥שׁ",
        "text_no_nikud": "ייבש",
        "lemma": "H3001",
        "strong": "H3001",
        "morph": "HVqi3ms"
      },
      {
        "text": "נִדַּ֖ף",
        "text_no_nikud": "נדף",
        "lemma": "H5086",
        "strong": "H5086",
        "morph": "HVNp3ms"
      },
      {
        "text": "וְ/אֵינֶֽ/נּוּ",
        "text_no_nikud": "ו/אינ/נו",
        "lemma": "Hc/H369",
        "strong": "Hc/H369",
        "morph": "HC/Tn/Sp3ms"
      }
    ]
  },
  {
    "chapter": 19,
    "verse": 8,
    "hebrew": "וְ/אָנוּ֙ הַ/דַּיָּגִ֔ים וְ/אָ֣בְל֔וּ כָּל מַשְׁלִיכֵ֥י בַ/יְא֖וֹר חַכָּ֑ה וּ/פֹרְשֵׂ֥י מִכְמֹ֛רֶת עַל פְּנֵי מַ֖יִם אֻמְלָֽלוּ",
    "hebrew_no_nikud": "ו/אנו ה/דיגים ו/אבלו כל משליכי ב/יאור חכה ו/פרשי מכמרת על פני מים אמללו",
    "words": [
      {
        "text": "וְ/אָנוּ֙",
        "text_no_nikud": "ו/אנו",
        "lemma": "Hc/H578",
        "strong": "Hc/H578",
        "morph": "HC/D"
      },
      {
        "text": "הַ/דַּיָּגִ֔ים",
        "text_no_nikud": "ה/דיגים",
        "lemma": "Hd/H1771",
        "strong": "Hd/H1771",
        "morph": "HTd/Ncmpa"
      },
      {
        "text": "וְ/אָ֣בְל֔וּ",
        "text_no_nikud": "ו/אבלו",
        "lemma": "Hc/H56",
        "strong": "Hc/H56",
        "morph": "HC/Vqq3cp"
      },
      {
        "text": "כָּל",
        "text_no_nikud": "כל",
        "lemma": "H3605",
        "strong": "H3605",
        "morph": "HNcmsc"
      },
      {
        "text": "מַשְׁלִיכֵ֥י",
        "text_no_nikud": "משליכי",
        "lemma": "H7993",
        "strong": "H7993",
        "morph": "HVhrmpc"
      },
      {
        "text": "בַ/יְא֖וֹר",
        "text_no_nikud": "ב/יאור",
        "lemma": "Hb/H2975",
        "strong": "Hb/H2975",
        "morph": "HRd/Np"
      },
      {
        "text": "חַכָּ֑ה",
        "text_no_nikud": "חכה",
        "lemma": "H2443",
        "strong": "H2443",
        "morph": "HNcfsa"
      },
      {
        "text": "וּ/פֹרְשֵׂ֥י",
        "text_no_nikud": "ו/פרשי",
        "lemma": "Hc/H6566",
        "strong": "Hc/H6566",
        "morph": "HC/Vqrmpc"
      },
      {
        "text": "מִכְמֹ֛רֶת",
        "text_no_nikud": "מכמרת",
        "lemma": "H4365",
        "strong": "H4365",
        "morph": "HNcfsa"
      },
      {
        "text": "עַל",
        "text_no_nikud": "על",
        "lemma": "H5921",
        "strong": "H5921",
        "morph": "HR"
      },
      {
        "text": "פְּנֵי",
        "text_no_nikud": "פני",
        "lemma": "H6440",
        "strong": "H6440",
        "morph": "HNcbpc"
      },
      {
        "text": "מַ֖יִם",
        "text_no_nikud": "מים",
        "lemma": "H4325",
        "strong": "H4325",
        "morph": "HNcmpa"
      },
      {
        "text": "אֻמְלָֽלוּ",
        "text_no_nikud": "אמללו",
        "lemma": "H535",
        "strong": "H535",
        "morph": "HVKp3cp"
      }
    ]
  },
  {
    "chapter": 19,
    "verse": 9,
    "hebrew": "וּ/בֹ֛שׁוּ עֹבְדֵ֥י פִשְׁתִּ֖ים שְׂרִיק֑וֹת וְ/אֹרְגִ֖ים חוֹרָֽי",
    "hebrew_no_nikud": "ו/בשו עבדי פשתים שריקות ו/ארגים חורי",
    "words": [
      {
        "text": "וּ/בֹ֛שׁוּ",
        "text_no_nikud": "ו/בשו",
        "lemma": "Hc/H954",
        "strong": "Hc/H954",
        "morph": "HC/Vqq3cp"
      },
      {
        "text": "עֹבְדֵ֥י",
        "text_no_nikud": "עבדי",
        "lemma": "H5647",
        "strong": "H5647",
        "morph": "HVqrmpc"
      },
      {
        "text": "פִשְׁתִּ֖ים",
        "text_no_nikud": "פשתים",
        "lemma": "H6593",
        "strong": "H6593",
        "morph": "HNcmpa"
      },
      {
        "text": "שְׂרִיק֑וֹת",
        "text_no_nikud": "שריקות",
        "lemma": "H8305",
        "strong": "H8305",
        "morph": "HAafpa"
      },
      {
        "text": "וְ/אֹרְגִ֖ים",
        "text_no_nikud": "ו/ארגים",
        "lemma": "Hc/H707",
        "strong": "Hc/H707",
        "morph": "HC/Vqrmpa"
      },
      {
        "text": "חוֹרָֽי",
        "text_no_nikud": "חורי",
        "lemma": "H2355",
        "strong": "H2355",
        "morph": "HNcmsa"
      }
    ]
  },
  {
    "chapter": 19,
    "verse": 10,
    "hebrew": "וְ/הָי֥וּ שָׁתֹתֶ֖י/הָ מְדֻכָּאִ֑ים כָּל עֹ֥שֵׂי שֶׂ֖כֶר אַגְמֵי נָֽפֶשׁ",
    "hebrew_no_nikud": "ו/היו שתתי/ה מדכאים כל עשי שכר אגמי נפש",
    "words": [
      {
        "text": "וְ/הָי֥וּ",
        "text_no_nikud": "ו/היו",
        "lemma": "Hc/H1961",
        "strong": "Hc/H1961",
        "morph": "HC/Vqq3cp"
      },
      {
        "text": "שָׁתֹתֶ֖י/הָ",
        "text_no_nikud": "שתתי/ה",
        "lemma": "H8356",
        "strong": "H8356",
        "morph": "HNcmpc/Sp3fs"
      },
      {
        "text": "מְדֻכָּאִ֑ים",
        "text_no_nikud": "מדכאים",
        "lemma": "H1792",
        "strong": "H1792",
        "morph": "HVPsmpa"
      },
      {
        "text": "כָּל",
        "text_no_nikud": "כל",
        "lemma": "H3605",
        "strong": "H3605",
        "morph": "HNcmsc"
      },
      {
        "text": "עֹ֥שֵׂי",
        "text_no_nikud": "עשי",
        "lemma": "H6213",
        "strong": "H6213",
        "morph": "HVqrmpc"
      },
      {
        "text": "שֶׂ֖כֶר",
        "text_no_nikud": "שכר",
        "lemma": "H7938",
        "strong": "H7938",
        "morph": "HNcmsa"
      },
      {
        "text": "אַגְמֵי",
        "text_no_nikud": "אגמי",
        "lemma": "H99",
        "strong": "H99",
        "morph": "HAampc"
      },
      {
        "text": "נָֽפֶשׁ",
        "text_no_nikud": "נפש",
        "lemma": "H5315",
        "strong": "H5315",
        "morph": "HNcbsa"
      }
    ]
  },
  {
    "chapter": 19,
    "verse": 11,
    "hebrew": "אַךְ אֱוִלִים֙ שָׂ֣רֵי צֹ֔עַן חַכְמֵי֙ יֹעֲצֵ֣י פַרְעֹ֔ה עֵצָ֖ה נִבְעָרָ֑ה אֵ֚יךְ תֹּאמְר֣וּ אֶל פַּרְעֹ֔ה בֶּן חֲכָמִ֥ים אֲנִ֖י בֶּן מַלְכֵי קֶֽדֶם",
    "hebrew_no_nikud": "אך אולים שרי צען חכמי יעצי פרעה עצה נבערה איך תאמרו אל פרעה בן חכמים אני בן מלכי קדם",
    "words": [
      {
        "text": "אַךְ",
        "text_no_nikud": "אך",
        "lemma": "H389",
        "strong": "H389",
        "morph": "HTa"
      },
      {
        "text": "אֱוִלִים֙",
        "text_no_nikud": "אולים",
        "lemma": "H191",
        "strong": "H191",
        "morph": "HAampa"
      },
      {
        "text": "שָׂ֣רֵי",
        "text_no_nikud": "שרי",
        "lemma": "H8269",
        "strong": "H8269",
        "morph": "HNcmpc"
      },
      {
        "text": "צֹ֔עַן",
        "text_no_nikud": "צען",
        "lemma": "H6814",
        "strong": "H6814",
        "morph": "HNp"
      },
      {
        "text": "חַכְמֵי֙",
        "text_no_nikud": "חכמי",
        "lemma": "H2450",
        "strong": "H2450",
        "morph": "HAampc"
      },
      {
        "text": "יֹעֲצֵ֣י",
        "text_no_nikud": "יעצי",
        "lemma": "H6098",
        "strong": "H6098",
        "morph": "HVqrmpc"
      },
      {
        "text": "פַרְעֹ֔ה",
        "text_no_nikud": "פרעה",
        "lemma": "H6547",
        "strong": "H6547",
        "morph": "HNp"
      },
      {
        "text": "עֵצָ֖ה",
        "text_no_nikud": "עצה",
        "lemma": "H6098",
        "strong": "H6098",
        "morph": "HNcfsa"
      },
      {
        "text": "נִבְעָרָ֑ה",
        "text_no_nikud": "נבערה",
        "lemma": "H1197",
        "strong": "H1197",
        "morph": "HVNrfsa"
      },
      {
        "text": "אֵ֚יךְ",
        "text_no_nikud": "איך",
        "lemma": "H349",
        "strong": "H349",
        "morph": "HTi"
      },
      {
        "text": "תֹּאמְר֣וּ",
        "text_no_nikud": "תאמרו",
        "lemma": "H559",
        "strong": "H559",
        "morph": "HVqi2mp"
      },
      {
        "text": "אֶל",
        "text_no_nikud": "אל",
        "lemma": "H413",
        "strong": "H413",
        "morph": "HR"
      },
      {
        "text": "פַּרְעֹ֔ה",
        "text_no_nikud": "פרעה",
        "lemma": "H6547",
        "strong": "H6547",
        "morph": "HNp"
      },
      {
        "text": "בֶּן",
        "text_no_nikud": "בן",
        "lemma": "H1121",
        "strong": "H1121",
        "morph": "HNcmsc"
      },
      {
        "text": "חֲכָמִ֥ים",
        "text_no_nikud": "חכמים",
        "lemma": "H2450",
        "strong": "H2450",
        "morph": "HAampa"
      },
      {
        "text": "אֲנִ֖י",
        "text_no_nikud": "אני",
        "lemma": "H589",
        "strong": "H589",
        "morph": "HPp1cs"
      },
      {
        "text": "בֶּן",
        "text_no_nikud": "בן",
        "lemma": "H1121",
        "strong": "H1121",
        "morph": "HNcmsc"
      },
      {
        "text": "מַלְכֵי",
        "text_no_nikud": "מלכי",
        "lemma": "H4428",
        "strong": "H4428",
        "morph": "HNcmpc"
      },
      {
        "text": "קֶֽדֶם",
        "text_no_nikud": "קדם",
        "lemma": "H6924",
        "strong": "H6924",
        "morph": "HNcmsa"
      }
    ]
  },
  {
    "chapter": 19,
    "verse": 12,
    "hebrew": "אַיָּ/ם֙ אֵפ֣וֹא חֲכָמֶ֔י/ךָ וְ/יַגִּ֥ידוּ נָ֖א לָ֑/ךְ וְ/יֵ֣דְע֔וּ מַה יָּעַ֛ץ יְהוָ֥ה צְבָא֖וֹת עַל מִצְרָֽיִם",
    "hebrew_no_nikud": "אי/ם אפוא חכמי/ך ו/יגידו נא ל/ך ו/ידעו מה יעץ יהוה צבאות על מצרים",
    "words": [
      {
        "text": "אַיָּ/ם֙",
        "text_no_nikud": "אי/ם",
        "lemma": "H335",
        "strong": "H335",
        "morph": "HTi/Sp3mp"
      },
      {
        "text": "אֵפ֣וֹא",
        "text_no_nikud": "אפוא",
        "lemma": "H645",
        "strong": "H645",
        "morph": "HD"
      },
      {
        "text": "חֲכָמֶ֔י/ךָ",
        "text_no_nikud": "חכמי/ך",
        "lemma": "H2450",
        "strong": "H2450",
        "morph": "HAampc/Sp2ms"
      },
      {
        "text": "וְ/יַגִּ֥ידוּ",
        "text_no_nikud": "ו/יגידו",
        "lemma": "Hc/H5046",
        "strong": "Hc/H5046",
        "morph": "HC/Vhj3mp"
      },
      {
        "text": "נָ֖א",
        "text_no_nikud": "נא",
        "lemma": "H4994",
        "strong": "H4994",
        "morph": "HTe"
      },
      {
        "text": "לָ֑/ךְ",
        "text_no_nikud": "ל/ך",
        "lemma": "Hl",
        "strong": "Hl",
        "morph": "HR/Sp2fs"
      },
      {
        "text": "וְ/יֵ֣דְע֔וּ",
        "text_no_nikud": "ו/ידעו",
        "lemma": "Hc/H3045",
        "strong": "Hc/H3045",
        "morph": "HC/Vqi3mp"
      },
      {
        "text": "מַה",
        "text_no_nikud": "מה",
        "lemma": "H4100",
        "strong": "H4100",
        "morph": "HTi"
      },
      {
        "text": "יָּעַ֛ץ",
        "text_no_nikud": "יעץ",
        "lemma": "H3289",
        "strong": "H3289",
        "morph": "HVqp3ms"
      },
      {
        "text": "יְהוָ֥ה",
        "text_no_nikud": "יהוה",
        "lemma": "H3068",
        "strong": "H3068",
        "morph": "HNp"
      },
      {
        "text": "צְבָא֖וֹת",
        "text_no_nikud": "צבאות",
        "lemma": "H6635",
        "strong": "H6635",
        "morph": "HNcbpa"
      },
      {
        "text": "עַל",
        "text_no_nikud": "על",
        "lemma": "H5921",
        "strong": "H5921",
        "morph": "HR"
      },
      {
        "text": "מִצְרָֽיִם",
        "text_no_nikud": "מצרים",
        "lemma": "H4714",
        "strong": "H4714",
        "morph": "HNp"
      }
    ]
  },
  {
    "chapter": 19,
    "verse": 13,
    "hebrew": "נֽוֹאֲלוּ֙ שָׂ֣רֵי צֹ֔עַן נִשְּׁא֖וּ שָׂ֣רֵי נֹ֑ף הִתְע֥וּ אֶת מִצְרַ֖יִם פִּנַּ֥ת שְׁבָטֶֽי/הָ",
    "hebrew_no_nikud": "נואלו שרי צען נשאו שרי נף התעו את מצרים פנת שבטי/ה",
    "words": [
      {
        "text": "נֽוֹאֲלוּ֙",
        "text_no_nikud": "נואלו",
        "lemma": "H2973",
        "strong": "H2973",
        "morph": "HVNp3cp"
      },
      {
        "text": "שָׂ֣רֵי",
        "text_no_nikud": "שרי",
        "lemma": "H8269",
        "strong": "H8269",
        "morph": "HNcmpc"
      },
      {
        "text": "צֹ֔עַן",
        "text_no_nikud": "צען",
        "lemma": "H6814",
        "strong": "H6814",
        "morph": "HNp"
      },
      {
        "text": "נִשְּׁא֖וּ",
        "text_no_nikud": "נשאו",
        "lemma": "H5377",
        "strong": "H5377",
        "morph": "HVNp3cp"
      },
      {
        "text": "שָׂ֣רֵי",
        "text_no_nikud": "שרי",
        "lemma": "H8269",
        "strong": "H8269",
        "morph": "HNcmpc"
      },
      {
        "text": "נֹ֑ף",
        "text_no_nikud": "נף",
        "lemma": "H5297",
        "strong": "H5297",
        "morph": "HNp"
      },
      {
        "text": "הִתְע֥וּ",
        "text_no_nikud": "התעו",
        "lemma": "H8582",
        "strong": "H8582",
        "morph": "HVhp3cp"
      },
      {
        "text": "אֶת",
        "text_no_nikud": "את",
        "lemma": "H853",
        "strong": "H853",
        "morph": "HTo"
      },
      {
        "text": "מִצְרַ֖יִם",
        "text_no_nikud": "מצרים",
        "lemma": "H4714",
        "strong": "H4714",
        "morph": "HNp"
      },
      {
        "text": "פִּנַּ֥ת",
        "text_no_nikud": "פנת",
        "lemma": "H6438",
        "strong": "H6438",
        "morph": "HNcfsc"
      },
      {
        "text": "שְׁבָטֶֽי/הָ",
        "text_no_nikud": "שבטי/ה",
        "lemma": "H7626",
        "strong": "H7626",
        "morph": "HNcmpc/Sp3fs"
      }
    ]
  },
  {
    "chapter": 19,
    "verse": 14,
    "hebrew": "יְהוָ֛ה מָסַ֥ךְ בְּ/קִרְבָּ֖/הּ ר֣וּחַ עִוְעִ֑ים וְ/הִתְע֤וּ אֶת מִצְרַ֨יִם֙ בְּ/כָֽל מַעֲשֵׂ֔/הוּ כְּ/הִתָּע֥וֹת שִׁכּ֖וֹר בְּ/קִיאֽ/וֹ",
    "hebrew_no_nikud": "יהוה מסך ב/קרב/ה רוח עועים ו/התעו את מצרים ב/כל מעש/הו כ/התעות שכור ב/קיא/ו",
    "words": [
      {
        "text": "יְהוָ֛ה",
        "text_no_nikud": "יהוה",
        "lemma": "H3068",
        "strong": "H3068",
        "morph": "HNp"
      },
      {
        "text": "מָסַ֥ךְ",
        "text_no_nikud": "מסך",
        "lemma": "H4537",
        "strong": "H4537",
        "morph": "HVqp3ms"
      },
      {
        "text": "בְּ/קִרְבָּ֖/הּ",
        "text_no_nikud": "ב/קרב/ה",
        "lemma": "Hb/H7130",
        "strong": "Hb/H7130",
        "morph": "HR/Ncmsc/Sp3fs"
      },
      {
        "text": "ר֣וּחַ",
        "text_no_nikud": "רוח",
        "lemma": "H7307",
        "strong": "H7307",
        "morph": "HNcbsc"
      },
      {
        "text": "עִוְעִ֑ים",
        "text_no_nikud": "עועים",
        "lemma": "H5773",
        "strong": "H5773",
        "morph": "HNcmpa"
      },
      {
        "text": "וְ/הִתְע֤וּ",
        "text_no_nikud": "ו/התעו",
        "lemma": "Hc/H8582",
        "strong": "Hc/H8582",
        "morph": "HC/Vhq3cp"
      },
      {
        "text": "אֶת",
        "text_no_nikud": "את",
        "lemma": "H853",
        "strong": "H853",
        "morph": "HTo"
      },
      {
        "text": "מִצְרַ֨יִם֙",
        "text_no_nikud": "מצרים",
        "lemma": "H4714",
        "strong": "H4714",
        "morph": "HNp"
      },
      {
        "text": "בְּ/כָֽל",
        "text_no_nikud": "ב/כל",
        "lemma": "Hb/H3605",
        "strong": "Hb/H3605",
        "morph": "HR/Ncmsc"
      },
      {
        "text": "מַעֲשֵׂ֔/הוּ",
        "text_no_nikud": "מעש/הו",
        "lemma": "H4639",
        "strong": "H4639",
        "morph": "HNcmsc/Sp3ms"
      },
      {
        "text": "כְּ/הִתָּע֥וֹת",
        "text_no_nikud": "כ/התעות",
        "lemma": "Hk/H8582",
        "strong": "Hk/H8582",
        "morph": "HR/VNc"
      },
      {
        "text": "שִׁכּ֖וֹר",
        "text_no_nikud": "שכור",
        "lemma": "H7910",
        "strong": "H7910",
        "morph": "HAamsa"
      },
      {
        "text": "בְּ/קִיאֽ/וֹ",
        "text_no_nikud": "ב/קיא/ו",
        "lemma": "Hb/H6892",
        "strong": "Hb/H6892",
        "morph": "HR/Ncmsc/Sp3ms"
      }
    ]
  },
  {
    "chapter": 19,
    "verse": 15,
    "hebrew": "וְ/לֹֽא יִהְיֶ֥ה לְ/מִצְרַ֖יִם מַֽעֲשֶׂ֑ה אֲשֶׁ֧ר יַעֲשֶׂ֛ה רֹ֥אשׁ וְ/זָנָ֖ב כִּפָּ֥ה וְ/אַגְמֽוֹן",
    "hebrew_no_nikud": "ו/לא יהיה ל/מצרים מעשה אשר יעשה ראש ו/זנב כפה ו/אגמון",
    "words": [
      {
        "text": "וְ/לֹֽא",
        "text_no_nikud": "ו/לא",
        "lemma": "Hc/H3808",
        "strong": "Hc/H3808",
        "morph": "HC/Tn"
      },
      {
        "text": "יִהְיֶ֥ה",
        "text_no_nikud": "יהיה",
        "lemma": "H1961",
        "strong": "H1961",
        "morph": "HVqi3ms"
      },
      {
        "text": "לְ/מִצְרַ֖יִם",
        "text_no_nikud": "ל/מצרים",
        "lemma": "Hl/H4714",
        "strong": "Hl/H4714",
        "morph": "HR/Np"
      },
      {
        "text": "מַֽעֲשֶׂ֑ה",
        "text_no_nikud": "מעשה",
        "lemma": "H4639",
        "strong": "H4639",
        "morph": "HNcmsa"
      },
      {
        "text": "אֲשֶׁ֧ר",
        "text_no_nikud": "אשר",
        "lemma": "H834",
        "strong": "H834",
        "morph": "HTr"
      },
      {
        "text": "יַעֲשֶׂ֛ה",
        "text_no_nikud": "יעשה",
        "lemma": "H6213",
        "strong": "H6213",
        "morph": "HVqi3ms"
      },
      {
        "text": "רֹ֥אשׁ",
        "text_no_nikud": "ראש",
        "lemma": "H7218",
        "strong": "H7218",
        "morph": "HNcmsa"
      },
      {
        "text": "וְ/זָנָ֖ב",
        "text_no_nikud": "ו/זנב",
        "lemma": "Hc/H2180",
        "strong": "Hc/H2180",
        "morph": "HC/Ncmsa"
      },
      {
        "text": "כִּפָּ֥ה",
        "text_no_nikud": "כפה",
        "lemma": "H3712",
        "strong": "H3712",
        "morph": "HNcfsa"
      },
      {
        "text": "וְ/אַגְמֽוֹן",
        "text_no_nikud": "ו/אגמון",
        "lemma": "Hc/H100",
        "strong": "Hc/H100",
        "morph": "HC/Ncmsa"
      }
    ]
  },
  {
    "chapter": 19,
    "verse": 16,
    "hebrew": "בַּ/יּ֣וֹם הַ/ה֔וּא יִֽהְיֶ֥ה מִצְרַ֖יִם כַּ/נָּשִׁ֑ים וְ/חָרַ֣ד וּ/פָחַ֗ד מִ/פְּנֵי֙ תְּנוּפַת֙ יַד יְהוָ֣ה צְבָא֔וֹת אֲשֶׁר ה֖וּא מֵנִ֥יף עָלָֽי/ו",
    "hebrew_no_nikud": "ב/יום ה/הוא יהיה מצרים כ/נשים ו/חרד ו/פחד מ/פני תנופת יד יהוה צבאות אשר הוא מניף עלי/ו",
    "words": [
      {
        "text": "בַּ/יּ֣וֹם",
        "text_no_nikud": "ב/יום",
        "lemma": "Hb/H3117",
        "strong": "Hb/H3117",
        "morph": "HRd/Ncmsa"
      },
      {
        "text": "הַ/ה֔וּא",
        "text_no_nikud": "ה/הוא",
        "lemma": "Hd/H1931",
        "strong": "Hd/H1931",
        "morph": "HTd/Pp3ms"
      },
      {
        "text": "יִֽהְיֶ֥ה",
        "text_no_nikud": "יהיה",
        "lemma": "H1961",
        "strong": "H1961",
        "morph": "HVqi3ms"
      },
      {
        "text": "מִצְרַ֖יִם",
        "text_no_nikud": "מצרים",
        "lemma": "H4714",
        "strong": "H4714",
        "morph": "HNp"
      },
      {
        "text": "כַּ/נָּשִׁ֑ים",
        "text_no_nikud": "כ/נשים",
        "lemma": "Hk/H802",
        "strong": "Hk/H802",
        "morph": "HRd/Ncfpa"
      },
      {
        "text": "וְ/חָרַ֣ד",
        "text_no_nikud": "ו/חרד",
        "lemma": "Hc/H2729",
        "strong": "Hc/H2729",
        "morph": "HC/Vqp3ms"
      },
      {
        "text": "וּ/פָחַ֗ד",
        "text_no_nikud": "ו/פחד",
        "lemma": "Hc/H6342",
        "strong": "Hc/H6342",
        "morph": "HC/Vqq3ms"
      },
      {
        "text": "מִ/פְּנֵי֙",
        "text_no_nikud": "מ/פני",
        "lemma": "Hm/H6440",
        "strong": "Hm/H6440",
        "morph": "HR/Ncbpc"
      },
      {
        "text": "תְּנוּפַת֙",
        "text_no_nikud": "תנופת",
        "lemma": "H8573",
        "strong": "H8573",
        "morph": "HNcfsc"
      },
      {
        "text": "יַד",
        "text_no_nikud": "יד",
        "lemma": "H3027",
        "strong": "H3027",
        "morph": "HNcbsc"
      },
      {
        "text": "יְהוָ֣ה",
        "text_no_nikud": "יהוה",
        "lemma": "H3068",
        "strong": "H3068",
        "morph": "HNp"
      },
      {
        "text": "צְבָא֔וֹת",
        "text_no_nikud": "צבאות",
        "lemma": "H6635",
        "strong": "H6635",
        "morph": "HNcbpa"
      },
      {
        "text": "אֲשֶׁר",
        "text_no_nikud": "אשר",
        "lemma": "H834",
        "strong": "H834",
        "morph": "HTr"
      },
      {
        "text": "ה֖וּא",
        "text_no_nikud": "הוא",
        "lemma": "H1931",
        "strong": "H1931",
        "morph": "HPp3ms"
      },
      {
        "text": "מֵנִ֥יף",
        "text_no_nikud": "מניף",
        "lemma": "H5130",
        "strong": "H5130",
        "morph": "HVhrmsa"
      },
      {
        "text": "עָלָֽי/ו",
        "text_no_nikud": "עלי/ו",
        "lemma": "H5921",
        "strong": "H5921",
        "morph": "HR/Sp3ms"
      }
    ]
  },
  {
    "chapter": 19,
    "verse": 17,
    "hebrew": "וְ֠/הָיְתָה אַדְמַ֨ת יְהוּדָ֤ה לְ/מִצְרַ֨יִם֙ לְ/חָגָּ֔א כֹּל֩ אֲשֶׁ֨ר יַזְכִּ֥יר אֹתָ֛/הּ אֵלָ֖י/ו יִפְחָ֑ד מִ/פְּנֵ֗י עֲצַת֙ יְהוָ֣ה צְבָא֔וֹת אֲשֶׁר ה֖וּא יוֹעֵ֥ץ עָלָֽי/ו",
    "hebrew_no_nikud": "ו/היתה אדמת יהודה ל/מצרים ל/חגא כל אשר יזכיר את/ה אלי/ו יפחד מ/פני עצת יהוה צבאות אשר הוא יועץ עלי/ו",
    "words": [
      {
        "text": "וְ֠/הָיְתָה",
        "text_no_nikud": "ו/היתה",
        "lemma": "Hc/H1961",
        "strong": "Hc/H1961",
        "morph": "HC/Vqq3fs"
      },
      {
        "text": "אַדְמַ֨ת",
        "text_no_nikud": "אדמת",
        "lemma": "H127",
        "strong": "H127",
        "morph": "HNcfsc"
      },
      {
        "text": "יְהוּדָ֤ה",
        "text_no_nikud": "יהודה",
        "lemma": "H3063",
        "strong": "H3063",
        "morph": "HNp"
      },
      {
        "text": "לְ/מִצְרַ֨יִם֙",
        "text_no_nikud": "ל/מצרים",
        "lemma": "Hl/H4714",
        "strong": "Hl/H4714",
        "morph": "HR/Np"
      },
      {
        "text": "לְ/חָגָּ֔א",
        "text_no_nikud": "ל/חגא",
        "lemma": "Hl/H2283",
        "strong": "Hl/H2283",
        "morph": "HR/Ncfsa"
      },
      {
        "text": "כֹּל֩",
        "text_no_nikud": "כל",
        "lemma": "H3605",
        "strong": "H3605",
        "morph": "HNcmsa"
      },
      {
        "text": "אֲשֶׁ֨ר",
        "text_no_nikud": "אשר",
        "lemma": "H834",
        "strong": "H834",
        "morph": "HTr"
      },
      {
        "text": "יַזְכִּ֥יר",
        "text_no_nikud": "יזכיר",
        "lemma": "H2142",
        "strong": "H2142",
        "morph": "HVhi3ms"
      },
      {
        "text": "אֹתָ֛/הּ",
        "text_no_nikud": "את/ה",
        "lemma": "H853",
        "strong": "H853",
        "morph": "HTo/Sp3fs"
      },
      {
        "text": "אֵלָ֖י/ו",
        "text_no_nikud": "אלי/ו",
        "lemma": "H413",
        "strong": "H413",
        "morph": "HR/Sp3ms"
      },
      {
        "text": "יִפְחָ֑ד",
        "text_no_nikud": "יפחד",
        "lemma": "H6342",
        "strong": "H6342",
        "morph": "HVqi3ms"
      },
      {
        "text": "מִ/פְּנֵ֗י",
        "text_no_nikud": "מ/פני",
        "lemma": "Hm/H6440",
        "strong": "Hm/H6440",
        "morph": "HR/Ncbpc"
      },
      {
        "text": "עֲצַת֙",
        "text_no_nikud": "עצת",
        "lemma": "H6098",
        "strong": "H6098",
        "morph": "HNcfsc"
      },
      {
        "text": "יְהוָ֣ה",
        "text_no_nikud": "יהוה",
        "lemma": "H3068",
        "strong": "H3068",
        "morph": "HNp"
      },
      {
        "text": "צְבָא֔וֹת",
        "text_no_nikud": "צבאות",
        "lemma": "H6635",
        "strong": "H6635",
        "morph": "HNcbpa"
      },
      {
        "text": "אֲשֶׁר",
        "text_no_nikud": "אשר",
        "lemma": "H834",
        "strong": "H834",
        "morph": "HTr"
      },
      {
        "text": "ה֖וּא",
        "text_no_nikud": "הוא",
        "lemma": "H1931",
        "strong": "H1931",
        "morph": "HPp3ms"
      },
      {
        "text": "יוֹעֵ֥ץ",
        "text_no_nikud": "יועץ",
        "lemma": "H3289",
        "strong": "H3289",
        "morph": "HVqrmsa"
      },
      {
        "text": "עָלָֽי/ו",
        "text_no_nikud": "עלי/ו",
        "lemma": "H5921",
        "strong": "H5921",
        "morph": "HR/Sp3ms"
      }
    ]
  },
  {
    "chapter": 19,
    "verse": 18,
    "hebrew": "בַּ/יּ֣וֹם הַ/ה֡וּא יִהְיוּ֩ חָמֵ֨שׁ עָרִ֜ים בְּ/אֶ֣רֶץ מִצְרַ֗יִם מְדַבְּרוֹת֙ שְׂפַ֣ת כְּנַ֔עַן וְ/נִשְׁבָּע֖וֹת לַ/יהוָ֣ה צְבָא֑וֹת עִ֣יר הַ/הֶ֔רֶס יֵאָמֵ֖ר לְ/אֶחָֽת",
    "hebrew_no_nikud": "ב/יום ה/הוא יהיו חמש ערים ב/ארץ מצרים מדברות שפת כנען ו/נשבעות ל/יהוה צבאות עיר ה/הרס יאמר ל/אחת",
    "words": [
      {
        "text": "בַּ/יּ֣וֹם",
        "text_no_nikud": "ב/יום",
        "lemma": "Hb/H3117",
        "strong": "Hb/H3117",
        "morph": "HRd/Ncmsa"
      },
      {
        "text": "הַ/ה֡וּא",
        "text_no_nikud": "ה/הוא",
        "lemma": "Hd/H1931",
        "strong": "Hd/H1931",
        "morph": "HTd/Pp3ms"
      },
      {
        "text": "יִהְיוּ֩",
        "text_no_nikud": "יהיו",
        "lemma": "H1961",
        "strong": "H1961",
        "morph": "HVqi3mp"
      },
      {
        "text": "חָמֵ֨שׁ",
        "text_no_nikud": "חמש",
        "lemma": "H2568",
        "strong": "H2568",
        "morph": "HAcfsa"
      },
      {
        "text": "עָרִ֜ים",
        "text_no_nikud": "ערים",
        "lemma": "H5892",
        "strong": "H5892",
        "morph": "HNcfpa"
      },
      {
        "text": "בְּ/אֶ֣רֶץ",
        "text_no_nikud": "ב/ארץ",
        "lemma": "Hb/H776",
        "strong": "Hb/H776",
        "morph": "HR/Ncbsc"
      },
      {
        "text": "מִצְרַ֗יִם",
        "text_no_nikud": "מצרים",
        "lemma": "H4714",
        "strong": "H4714",
        "morph": "HNp"
      },
      {
        "text": "מְדַבְּרוֹת֙",
        "text_no_nikud": "מדברות",
        "lemma": "H1696",
        "strong": "H1696",
        "morph": "HVprfpa"
      },
      {
        "text": "שְׂפַ֣ת",
        "text_no_nikud": "שפת",
        "lemma": "H8193",
        "strong": "H8193",
        "morph": "HNcfsc"
      },
      {
        "text": "כְּנַ֔עַן",
        "text_no_nikud": "כנען",
        "lemma": "H3667",
        "strong": "H3667",
        "morph": "HNp"
      },
      {
        "text": "וְ/נִשְׁבָּע֖וֹת",
        "text_no_nikud": "ו/נשבעות",
        "lemma": "Hc/H7650",
        "strong": "Hc/H7650",
        "morph": "HC/VNrfpa"
      },
      {
        "text": "לַ/יהוָ֣ה",
        "text_no_nikud": "ל/יהוה",
        "lemma": "Hl/H3068",
        "strong": "Hl/H3068",
        "morph": "HR/Np"
      },
      {
        "text": "צְבָא֑וֹת",
        "text_no_nikud": "צבאות",
        "lemma": "H6635",
        "strong": "H6635",
        "morph": "HNcbpa"
      },
      {
        "text": "עִ֣יר",
        "text_no_nikud": "עיר",
        "lemma": "H5892",
        "strong": "H5892",
        "morph": "HNcfsc"
      },
      {
        "text": "הַ/הֶ֔רֶס",
        "text_no_nikud": "ה/הרס",
        "lemma": "Hd/H2041",
        "strong": "Hd/H2041",
        "morph": "HTd/Ncmsa"
      },
      {
        "text": "יֵאָמֵ֖ר",
        "text_no_nikud": "יאמר",
        "lemma": "H559",
        "strong": "H559",
        "morph": "HVNi3ms"
      },
      {
        "text": "לְ/אֶחָֽת",
        "text_no_nikud": "ל/אחת",
        "lemma": "Hl/H259",
        "strong": "Hl/H259",
        "morph": "HR/Acfsa"
      }
    ]
  },
  {
    "chapter": 19,
    "verse": 19,
    "hebrew": "בַּ/יּ֣וֹם הַ/ה֗וּא יִֽהְיֶ֤ה מִזְבֵּ֨חַ֙ לַֽ/יהוָ֔ה בְּ/ת֖וֹךְ אֶ֣רֶץ מִצְרָ֑יִם וּ/מַצֵּבָ֥ה אֵֽצֶל גְּבוּלָ֖/הּ לַֽ/יהוָֽה",
    "hebrew_no_nikud": "ב/יום ה/הוא יהיה מזבח ל/יהוה ב/תוך ארץ מצרים ו/מצבה אצל גבול/ה ל/יהוה",
    "words": [
      {
        "text": "בַּ/יּ֣וֹם",
        "text_no_nikud": "ב/יום",
        "lemma": "Hb/H3117",
        "strong": "Hb/H3117",
        "morph": "HRd/Ncmsa"
      },
      {
        "text": "הַ/ה֗וּא",
        "text_no_nikud": "ה/הוא",
        "lemma": "Hd/H1931",
        "strong": "Hd/H1931",
        "morph": "HTd/Pp3ms"
      },
      {
        "text": "יִֽהְיֶ֤ה",
        "text_no_nikud": "יהיה",
        "lemma": "H1961",
        "strong": "H1961",
        "morph": "HVqi3ms"
      },
      {
        "text": "מִזְבֵּ֨חַ֙",
        "text_no_nikud": "מזבח",
        "lemma": "H4196",
        "strong": "H4196",
        "morph": "HNcmsa"
      },
      {
        "text": "לַֽ/יהוָ֔ה",
        "text_no_nikud": "ל/יהוה",
        "lemma": "Hl/H3068",
        "strong": "Hl/H3068",
        "morph": "HR/Np"
      },
      {
        "text": "בְּ/ת֖וֹךְ",
        "text_no_nikud": "ב/תוך",
        "lemma": "Hb/H8432",
        "strong": "Hb/H8432",
        "morph": "HR/Ncmsc"
      },
      {
        "text": "אֶ֣רֶץ",
        "text_no_nikud": "ארץ",
        "lemma": "H776",
        "strong": "H776",
        "morph": "HNcbsc"
      },
      {
        "text": "מִצְרָ֑יִם",
        "text_no_nikud": "מצרים",
        "lemma": "H4714",
        "strong": "H4714",
        "morph": "HNp"
      },
      {
        "text": "וּ/מַצֵּבָ֥ה",
        "text_no_nikud": "ו/מצבה",
        "lemma": "Hc/H4676",
        "strong": "Hc/H4676",
        "morph": "HC/Ncfsa"
      },
      {
        "text": "אֵֽצֶל",
        "text_no_nikud": "אצל",
        "lemma": "H681",
        "strong": "H681",
        "morph": "HR"
      },
      {
        "text": "גְּבוּלָ֖/הּ",
        "text_no_nikud": "גבול/ה",
        "lemma": "H1366",
        "strong": "H1366",
        "morph": "HNcmsc/Sp3fs"
      },
      {
        "text": "לַֽ/יהוָֽה",
        "text_no_nikud": "ל/יהוה",
        "lemma": "Hl/H3068",
        "strong": "Hl/H3068",
        "morph": "HR/Np"
      }
    ]
  },
  {
    "chapter": 19,
    "verse": 20,
    "hebrew": "וְ/הָיָ֨ה לְ/א֥וֹת וּ/לְ/עֵ֛ד לַֽ/יהוָ֥ה צְבָא֖וֹת בְּ/אֶ֣רֶץ מִצְרָ֑יִם כִּֽי יִצְעֲק֤וּ אֶל יְהוָה֙ מִ/פְּנֵ֣י לֹֽחֲצִ֔ים וְ/יִשְׁלַ֥ח לָ/הֶ֛ם מוֹשִׁ֥יעַ וָ/רָ֖ב וְ/הִצִּילָֽ/ם",
    "hebrew_no_nikud": "ו/היה ל/אות ו/ל/עד ל/יהוה צבאות ב/ארץ מצרים כי יצעקו אל יהוה מ/פני לחצים ו/ישלח ל/הם מושיע ו/רב ו/הציל/ם",
    "words": [
      {
        "text": "וְ/הָיָ֨ה",
        "text_no_nikud": "ו/היה",
        "lemma": "Hc/H1961",
        "strong": "Hc/H1961",
        "morph": "HC/Vqq3ms"
      },
      {
        "text": "לְ/א֥וֹת",
        "text_no_nikud": "ל/אות",
        "lemma": "Hl/H226",
        "strong": "Hl/H226",
        "morph": "HR/Ncbsa"
      },
      {
        "text": "וּ/לְ/עֵ֛ד",
        "text_no_nikud": "ו/ל/עד",
        "lemma": "Hc/Hl/H5707",
        "strong": "Hc/Hl/H5707",
        "morph": "HC/R/Ncmsa"
      },
      {
        "text": "לַֽ/יהוָ֥ה",
        "text_no_nikud": "ל/יהוה",
        "lemma": "Hl/H3068",
        "strong": "Hl/H3068",
        "morph": "HR/Np"
      },
      {
        "text": "צְבָא֖וֹת",
        "text_no_nikud": "צבאות",
        "lemma": "H6635",
        "strong": "H6635",
        "morph": "HNcbpa"
      },
      {
        "text": "בְּ/אֶ֣רֶץ",
        "text_no_nikud": "ב/ארץ",
        "lemma": "Hb/H776",
        "strong": "Hb/H776",
        "morph": "HR/Ncbsc"
      },
      {
        "text": "מִצְרָ֑יִם",
        "text_no_nikud": "מצרים",
        "lemma": "H4714",
        "strong": "H4714",
        "morph": "HNp"
      },
      {
        "text": "כִּֽי",
        "text_no_nikud": "כי",
        "lemma": "H3588",
        "strong": "H3588",
        "morph": "HC"
      },
      {
        "text": "יִצְעֲק֤וּ",
        "text_no_nikud": "יצעקו",
        "lemma": "H6817",
        "strong": "H6817",
        "morph": "HVqi3mp"
      },
      {
        "text": "אֶל",
        "text_no_nikud": "אל",
        "lemma": "H413",
        "strong": "H413",
        "morph": "HR"
      },
      {
        "text": "יְהוָה֙",
        "text_no_nikud": "יהוה",
        "lemma": "H3068",
        "strong": "H3068",
        "morph": "HNp"
      },
      {
        "text": "מִ/פְּנֵ֣י",
        "text_no_nikud": "מ/פני",
        "lemma": "Hm/H6440",
        "strong": "Hm/H6440",
        "morph": "HR/Ncbpc"
      },
      {
        "text": "לֹֽחֲצִ֔ים",
        "text_no_nikud": "לחצים",
        "lemma": "H3905",
        "strong": "H3905",
        "morph": "HVqrmpa"
      },
      {
        "text": "וְ/יִשְׁלַ֥ח",
        "text_no_nikud": "ו/ישלח",
        "lemma": "Hc/H7971",
        "strong": "Hc/H7971",
        "morph": "HC/Vqi3ms"
      },
      {
        "text": "לָ/הֶ֛ם",
        "text_no_nikud": "ל/הם",
        "lemma": "Hl",
        "strong": "Hl",
        "morph": "HR/Sp3mp"
      },
      {
        "text": "מוֹשִׁ֥יעַ",
        "text_no_nikud": "מושיע",
        "lemma": "H3467",
        "strong": "H3467",
        "morph": "HVhrmsa"
      },
      {
        "text": "וָ/רָ֖ב",
        "text_no_nikud": "ו/רב",
        "lemma": "Hc/H7227",
        "strong": "Hc/H7227",
        "morph": "HC/Vqrmsa"
      },
      {
        "text": "וְ/הִצִּילָֽ/ם",
        "text_no_nikud": "ו/הציל/ם",
        "lemma": "Hc/H5337",
        "strong": "Hc/H5337",
        "morph": "HC/Vhq3ms/Sp3mp"
      }
    ]
  },
  {
    "chapter": 19,
    "verse": 21,
    "hebrew": "וְ/נוֹדַ֤ע יְהוָה֙ לְ/מִצְרַ֔יִם וְ/יָדְע֥וּ מִצְרַ֛יִם אֶת יְהוָ֖ה בַּ/יּ֣וֹם הַ/ה֑וּא וְ/עָֽבְדוּ֙ זֶ֣בַח וּ/מִנְחָ֔ה וְ/נָדְרוּ נֵ֥דֶר לַֽ/יהוָ֖ה וְ/שִׁלֵּֽמוּ",
    "hebrew_no_nikud": "ו/נודע יהוה ל/מצרים ו/ידעו מצרים את יהוה ב/יום ה/הוא ו/עבדו זבח ו/מנחה ו/נדרו נדר ל/יהוה ו/שלמו",
    "words": [
      {
        "text": "וְ/נוֹדַ֤ע",
        "text_no_nikud": "ו/נודע",
        "lemma": "Hc/H3045",
        "strong": "Hc/H3045",
        "morph": "HC/VNq3ms"
      },
      {
        "text": "יְהוָה֙",
        "text_no_nikud": "יהוה",
        "lemma": "H3068",
        "strong": "H3068",
        "morph": "HNp"
      },
      {
        "text": "לְ/מִצְרַ֔יִם",
        "text_no_nikud": "ל/מצרים",
        "lemma": "Hl/H4714",
        "strong": "Hl/H4714",
        "morph": "HR/Np"
      },
      {
        "text": "וְ/יָדְע֥וּ",
        "text_no_nikud": "ו/ידעו",
        "lemma": "Hc/H3045",
        "strong": "Hc/H3045",
        "morph": "HC/Vqq3cp"
      },
      {
        "text": "מִצְרַ֛יִם",
        "text_no_nikud": "מצרים",
        "lemma": "H4714",
        "strong": "H4714",
        "morph": "HNp"
      },
      {
        "text": "אֶת",
        "text_no_nikud": "את",
        "lemma": "H853",
        "strong": "H853",
        "morph": "HTo"
      },
      {
        "text": "יְהוָ֖ה",
        "text_no_nikud": "יהוה",
        "lemma": "H3068",
        "strong": "H3068",
        "morph": "HNp"
      },
      {
        "text": "בַּ/יּ֣וֹם",
        "text_no_nikud": "ב/יום",
        "lemma": "Hb/H3117",
        "strong": "Hb/H3117",
        "morph": "HRd/Ncmsa"
      },
      {
        "text": "הַ/ה֑וּא",
        "text_no_nikud": "ה/הוא",
        "lemma": "Hd/H1931",
        "strong": "Hd/H1931",
        "morph": "HTd/Pp3ms"
      },
      {
        "text": "וְ/עָֽבְדוּ֙",
        "text_no_nikud": "ו/עבדו",
        "lemma": "Hc/H5647",
        "strong": "Hc/H5647",
        "morph": "HC/Vqq3cp"
      },
      {
        "text": "זֶ֣בַח",
        "text_no_nikud": "זבח",
        "lemma": "H2077",
        "strong": "H2077",
        "morph": "HNcmsa"
      },
      {
        "text": "וּ/מִנְחָ֔ה",
        "text_no_nikud": "ו/מנחה",
        "lemma": "Hc/H4503",
        "strong": "Hc/H4503",
        "morph": "HC/Ncfsa"
      },
      {
        "text": "וְ/נָדְרוּ",
        "text_no_nikud": "ו/נדרו",
        "lemma": "Hc/H5087",
        "strong": "Hc/H5087",
        "morph": "HC/Vqq3cp"
      },
      {
        "text": "נֵ֥דֶר",
        "text_no_nikud": "נדר",
        "lemma": "H5088",
        "strong": "H5088",
        "morph": "HNcmsa"
      },
      {
        "text": "לַֽ/יהוָ֖ה",
        "text_no_nikud": "ל/יהוה",
        "lemma": "Hl/H3068",
        "strong": "Hl/H3068",
        "morph": "HR/Np"
      },
      {
        "text": "וְ/שִׁלֵּֽמוּ",
        "text_no_nikud": "ו/שלמו",
        "lemma": "Hc/H7999",
        "strong": "Hc/H7999",
        "morph": "HC/Vpq3cp"
      }
    ]
  },
  {
    "chapter": 19,
    "verse": 22,
    "hebrew": "וְ/נָגַ֧ף יְהוָ֛ה אֶת מִצְרַ֖יִם נָגֹ֣ף וְ/רָפ֑וֹא וְ/שָׁ֨בוּ֙ עַד יְהוָ֔ה וְ/נֶעְתַּ֥ר לָ/הֶ֖ם וּ/רְפָאָֽ/ם",
    "hebrew_no_nikud": "ו/נגף יהוה את מצרים נגף ו/רפוא ו/שבו עד יהוה ו/נעתר ל/הם ו/רפא/ם",
    "words": [
      {
        "text": "וְ/נָגַ֧ף",
        "text_no_nikud": "ו/נגף",
        "lemma": "Hc/H5062",
        "strong": "Hc/H5062",
        "morph": "HC/Vqq3ms"
      },
      {
        "text": "יְהוָ֛ה",
        "text_no_nikud": "יהוה",
        "lemma": "H3068",
        "strong": "H3068",
        "morph": "HNp"
      },
      {
        "text": "אֶת",
        "text_no_nikud": "את",
        "lemma": "H853",
        "strong": "H853",
        "morph": "HTo"
      },
      {
        "text": "מִצְרַ֖יִם",
        "text_no_nikud": "מצרים",
        "lemma": "H4714",
        "strong": "H4714",
        "morph": "HNp"
      },
      {
        "text": "נָגֹ֣ף",
        "text_no_nikud": "נגף",
        "lemma": "H5062",
        "strong": "H5062",
        "morph": "HVqa"
      },
      {
        "text": "וְ/רָפ֑וֹא",
        "text_no_nikud": "ו/רפוא",
        "lemma": "Hc/H7495",
        "strong": "Hc/H7495",
        "morph": "HC/Vqa"
      },
      {
        "text": "וְ/שָׁ֨בוּ֙",
        "text_no_nikud": "ו/שבו",
        "lemma": "Hc/H7725",
        "strong": "Hc/H7725",
        "morph": "HC/Vqq3cp"
      },
      {
        "text": "עַד",
        "text_no_nikud": "עד",
        "lemma": "H5704",
        "strong": "H5704",
        "morph": "HR"
      },
      {
        "text": "יְהוָ֔ה",
        "text_no_nikud": "יהוה",
        "lemma": "H3068",
        "strong": "H3068",
        "morph": "HNp"
      },
      {
        "text": "וְ/נֶעְתַּ֥ר",
        "text_no_nikud": "ו/נעתר",
        "lemma": "Hc/H6279",
        "strong": "Hc/H6279",
        "morph": "HC/VNq3ms"
      },
      {
        "text": "לָ/הֶ֖ם",
        "text_no_nikud": "ל/הם",
        "lemma": "Hl",
        "strong": "Hl",
        "morph": "HR/Sp3mp"
      },
      {
        "text": "וּ/רְפָאָֽ/ם",
        "text_no_nikud": "ו/רפא/ם",
        "lemma": "Hc/H7495",
        "strong": "Hc/H7495",
        "morph": "HC/Vqq3ms/Sp3mp"
      }
    ]
  },
  {
    "chapter": 19,
    "verse": 23,
    "hebrew": "בַּ/יּ֣וֹם הַ/ה֗וּא תִּהְיֶ֨ה מְסִלָּ֤ה מִ/מִּצְרַ֨יִם֙ אַשּׁ֔וּרָ/ה וּ/בָֽא אַשּׁ֥וּר בְּ/מִצְרַ֖יִם וּ/מִצְרַ֣יִם בְּ/אַשּׁ֑וּר וְ/עָבְד֥וּ מִצְרַ֖יִם אֶת אַשּֽׁוּר",
    "hebrew_no_nikud": "ב/יום ה/הוא תהיה מסלה מ/מצרים אשור/ה ו/בא אשור ב/מצרים ו/מצרים ב/אשור ו/עבדו מצרים את אשור",
    "words": [
      {
        "text": "בַּ/יּ֣וֹם",
        "text_no_nikud": "ב/יום",
        "lemma": "Hb/H3117",
        "strong": "Hb/H3117",
        "morph": "HRd/Ncmsa"
      },
      {
        "text": "הַ/ה֗וּא",
        "text_no_nikud": "ה/הוא",
        "lemma": "Hd/H1931",
        "strong": "Hd/H1931",
        "morph": "HTd/Pp3ms"
      },
      {
        "text": "תִּהְיֶ֨ה",
        "text_no_nikud": "תהיה",
        "lemma": "H1961",
        "strong": "H1961",
        "morph": "HVqi3fs"
      },
      {
        "text": "מְסִלָּ֤ה",
        "text_no_nikud": "מסלה",
        "lemma": "H4546",
        "strong": "H4546",
        "morph": "HNcfsa"
      },
      {
        "text": "מִ/מִּצְרַ֨יִם֙",
        "text_no_nikud": "מ/מצרים",
        "lemma": "Hm/H4714",
        "strong": "Hm/H4714",
        "morph": "HR/Np"
      },
      {
        "text": "אַשּׁ֔וּרָ/ה",
        "text_no_nikud": "אשור/ה",
        "lemma": "H804",
        "strong": "H804",
        "morph": "HNp/Sd"
      },
      {
        "text": "וּ/בָֽא",
        "text_no_nikud": "ו/בא",
        "lemma": "Hc/H935",
        "strong": "Hc/H935",
        "morph": "HC/Vqq3ms"
      },
      {
        "text": "אַשּׁ֥וּר",
        "text_no_nikud": "אשור",
        "lemma": "H804",
        "strong": "H804",
        "morph": "HNp"
      },
      {
        "text": "בְּ/מִצְרַ֖יִם",
        "text_no_nikud": "ב/מצרים",
        "lemma": "Hb/H4714",
        "strong": "Hb/H4714",
        "morph": "HR/Np"
      },
      {
        "text": "וּ/מִצְרַ֣יִם",
        "text_no_nikud": "ו/מצרים",
        "lemma": "Hc/H4714",
        "strong": "Hc/H4714",
        "morph": "HC/Np"
      },
      {
        "text": "בְּ/אַשּׁ֑וּר",
        "text_no_nikud": "ב/אשור",
        "lemma": "Hb/H804",
        "strong": "Hb/H804",
        "morph": "HR/Np"
      },
      {
        "text": "וְ/עָבְד֥וּ",
        "text_no_nikud": "ו/עבדו",
        "lemma": "Hc/H5647",
        "strong": "Hc/H5647",
        "morph": "HC/Vqq3cp"
      },
      {
        "text": "מִצְרַ֖יִם",
        "text_no_nikud": "מצרים",
        "lemma": "H4714",
        "strong": "H4714",
        "morph": "HNp"
      },
      {
        "text": "אֶת",
        "text_no_nikud": "את",
        "lemma": "H854",
        "strong": "H854",
        "morph": "HR"
      },
      {
        "text": "אַשּֽׁוּר",
        "text_no_nikud": "אשור",
        "lemma": "H804",
        "strong": "H804",
        "morph": "HNp"
      }
    ]
  },
  {
    "chapter": 19,
    "verse": 24,
    "hebrew": "בַּ/יּ֣וֹם הַ/ה֗וּא יִהְיֶ֤ה יִשְׂרָאֵל֙ שְׁלִ֣ישִׁיָּ֔ה לְ/מִצְרַ֖יִם וּ/לְ/אַשּׁ֑וּר בְּרָכָ֖ה בְּ/קֶ֥רֶב הָ/אָֽרֶץ",
    "hebrew_no_nikud": "ב/יום ה/הוא יהיה ישראל שלישיה ל/מצרים ו/ל/אשור ברכה ב/קרב ה/ארץ",
    "words": [
      {
        "text": "בַּ/יּ֣וֹם",
        "text_no_nikud": "ב/יום",
        "lemma": "Hb/H3117",
        "strong": "Hb/H3117",
        "morph": "HRd/Ncmsa"
      },
      {
        "text": "הַ/ה֗וּא",
        "text_no_nikud": "ה/הוא",
        "lemma": "Hd/H1931",
        "strong": "Hd/H1931",
        "morph": "HTd/Pp3ms"
      },
      {
        "text": "יִהְיֶ֤ה",
        "text_no_nikud": "יהיה",
        "lemma": "H1961",
        "strong": "H1961",
        "morph": "HVqi3ms"
      },
      {
        "text": "יִשְׂרָאֵל֙",
        "text_no_nikud": "ישראל",
        "lemma": "H3478",
        "strong": "H3478",
        "morph": "HNp"
      },
      {
        "text": "שְׁלִ֣ישִׁיָּ֔ה",
        "text_no_nikud": "שלישיה",
        "lemma": "H7992",
        "strong": "H7992",
        "morph": "HAofsa"
      },
      {
        "text": "לְ/מִצְרַ֖יִם",
        "text_no_nikud": "ל/מצרים",
        "lemma": "Hl/H4714",
        "strong": "Hl/H4714",
        "morph": "HR/Np"
      },
      {
        "text": "וּ/לְ/אַשּׁ֑וּר",
        "text_no_nikud": "ו/ל/אשור",
        "lemma": "Hc/Hl/H804",
        "strong": "Hc/Hl/H804",
        "morph": "HC/R/Np"
      },
      {
        "text": "בְּרָכָ֖ה",
        "text_no_nikud": "ברכה",
        "lemma": "H1293",
        "strong": "H1293",
        "morph": "HNcfsa"
      },
      {
        "text": "בְּ/קֶ֥רֶב",
        "text_no_nikud": "ב/קרב",
        "lemma": "Hb/H7130",
        "strong": "Hb/H7130",
        "morph": "HR/Ncmsc"
      },
      {
        "text": "הָ/אָֽרֶץ",
        "text_no_nikud": "ה/ארץ",
        "lemma": "Hd/H776",
        "strong": "Hd/H776",
        "morph": "HTd/Ncbsa"
      }
    ]
  },
  {
    "chapter": 19,
    "verse": 25,
    "hebrew": "אֲשֶׁ֧ר בֵּרֲכ֛/וֹ יְהוָ֥ה צְבָא֖וֹת לֵ/אמֹ֑ר בָּר֨וּךְ עַמִּ֜/י מִצְרַ֗יִם וּ/מַעֲשֵׂ֤ה יָדַ/י֙ אַשּׁ֔וּר וְ/נַחֲלָתִ֖/י יִשְׂרָאֵֽל",
    "hebrew_no_nikud": "אשר ברכ/ו יהוה צבאות ל/אמר ברוך עמ/י מצרים ו/מעשה יד/י אשור ו/נחלת/י ישראל",
    "words": [
      {
        "text": "אֲשֶׁ֧ר",
        "text_no_nikud": "אשר",
        "lemma": "H834",
        "strong": "H834",
        "morph": "HTr"
      },
      {
        "text": "בֵּרֲכ֛/וֹ",
        "text_no_nikud": "ברכ/ו",
        "lemma": "H1288",
        "strong": "H1288",
        "morph": "HVpp3ms/Sp3ms"
      },
      {
        "text": "יְהוָ֥ה",
        "text_no_nikud": "יהוה",
        "lemma": "H3068",
        "strong": "H3068",
        "morph": "HNp"
      },
      {
        "text": "צְבָא֖וֹת",
        "text_no_nikud": "צבאות",
        "lemma": "H6635",
        "strong": "H6635",
        "morph": "HNcbpa"
      },
      {
        "text": "לֵ/אמֹ֑ר",
        "text_no_nikud": "ל/אמר",
        "lemma": "Hl/H559",
        "strong": "Hl/H559",
        "morph": "HR/Vqc"
      },
      {
        "text": "בָּר֨וּךְ",
        "text_no_nikud": "ברוך",
        "lemma": "H1288",
        "strong": "H1288",
        "morph": "HVqsmsa"
      },
      {
        "text": "עַמִּ֜/י",
        "text_no_nikud": "עמ/י",
        "lemma": "H5971",
        "strong": "H5971",
        "morph": "HNcmsc/Sp1cs"
      },
      {
        "text": "מִצְרַ֗יִם",
        "text_no_nikud": "מצרים",
        "lemma": "H4714",
        "strong": "H4714",
        "morph": "HNp"
      },
      {
        "text": "וּ/מַעֲשֵׂ֤ה",
        "text_no_nikud": "ו/מעשה",
        "lemma": "Hc/H4639",
        "strong": "Hc/H4639",
        "morph": "HC/Ncmsc"
      },
      {
        "text": "יָדַ/י֙",
        "text_no_nikud": "יד/י",
        "lemma": "H3027",
        "strong": "H3027",
        "morph": "HNcbdc/Sp1cs"
      },
      {
        "text": "אַשּׁ֔וּר",
        "text_no_nikud": "אשור",
        "lemma": "H804",
        "strong": "H804",
        "morph": "HNp"
      },
      {
        "text": "וְ/נַחֲלָתִ֖/י",
        "text_no_nikud": "ו/נחלת/י",
        "lemma": "Hc/H5159",
        "strong": "Hc/H5159",
        "morph": "HC/Ncfsc/Sp1cs"
      },
      {
        "text": "יִשְׂרָאֵֽל",
        "text_no_nikud": "ישראל",
        "lemma": "H3478",
        "strong": "H3478",
        "morph": "HNp"
      }
    ]
  }
]