{
  "strong_number": "H2096",
  "lemma": "זֹהַר",
  "normalized": "זהר",
  "pronunciation": "zo'-har",
  "transliteration": "zôhar",
  "definitions": [
    {
      "text": "be light",
      "source": "bdb",
      "order": 1,
      "sense": "0"
    },
    {
      "text": "shining",
      "source": "bdb",
      "order": 2,
      "sense": "0"
    },
    {
      "text": "send out light",
      "source": "bdb",
      "order": 3,
      "sense": "0"
    },
    {
      "text": "shine",
      "source": "bdb",
      "order": 4,
      "sense": "0"
    }
  ],
  "sources": {
    "strongs": false,
    "bdb": true
  },
  "occurrences": {
    "total": 2,
    "references": [
      "dan.12.3",
      "ezek.8.2"
    ]
  },
  "is_root": false,
  "root_ref": "H2094"
}