{
  "strong_number": "H3893",
  "lemma": "לֵחַ",
  "normalized": "לח",
  "pronunciation": "lay'-akh",
  "transliteration": "lêach",
  "definitions": [
    {
      "text": "moisten, cool",
      "source": "bdb",
      "order": 1,
      "sense": "0"
    },
    {
      "text": "be moistened",
      "source": "bdb",
      "order": 2,
      "sense": "0"
    },
    {
      "text": "moisten thoroughly",
      "source": "bdb",
      "order": 3,
      "sense": "0"
    },
    {
      "text": "moist, fresh",
      "source": "bdb",
      "order": 4,
      "sense": "0"
    },
    {
      "text": "moisture, freshness",
      "source": "bdb",
      "order": 5,
      "sense": "0"
    }
  ],
  "sources": {
    "strongs": false,
    "bdb": true
  },
  "occurrences": {
    "total": 1,
    "references": [
      "deut.34.7"
    ]
  },
  "is_root": false,
  "root_ref": "H3892"
}