{
  "strong_number": "H4225",
  "lemma": "מַחְבֶּרֶת",
  "normalized": "מחברת",
  "pronunciation": "makh-beh'-reth",
  "transliteration": "machbereth",
  "definitions": [
    {
      "text": "thing joined",
      "source": "bdb",
      "order": 1,
      "sense": "0"
    },
    {
      "text": "place of joining",
      "source": "bdb",
      "order": 2,
      "sense": "0"
    }
  ],
  "sources": {
    "strongs": false,
    "bdb": true
  },
  "occurrences": {
    "total": 7,
    "references": [
      "exod.26.4",
      "exod.26.5",
      "exod.28.27",
      "exod.36.11",
      "exod.36.12",
      "exod.36.17",
      "exod.39.20"
    ]
  },
  "is_root": false,
  "root_ref": "H2266"
}