{
  "strong_number": "H5671",
  "lemma": "עַבְטִיט",
  "normalized": "עבטיט",
  "pronunciation": "ab-teet'",
  "transliteration": "ʻabṭîyṭ",
  "definitions": [
    {
      "text": "weight of pledges",
      "source": "bdb",
      "order": 1,
      "sense": "0"
    },
    {
      "text": "heavy debts",
      "source": "bdb",
      "order": 2,
      "sense": "0"
    }
  ],
  "sources": {
    "strongs": false,
    "bdb": true
  },
  "occurrences": {
    "total": 1,
    "references": [
      "hab.2.6"
    ]
  },
  "is_root": false,
  "root_ref": "H5670"
}