{
  "strong_number": "H7880",
  "lemma": "שִׂיחַ",
  "normalized": "שיח",
  "pronunciation": "see'-akh",
  "transliteration": "sîyach",
  "definitions": [
    {
      "text": "muse",
      "source": "bdb",
      "order": 1,
      "sense": "0"
    },
    {
      "text": "complain",
      "source": "bdb",
      "order": 2,
      "sense": "0"
    },
    {
      "text": "talk",
      "source": "bdb",
      "order": 3,
      "sense": "0"
    },
    {
      "text": "complain",
      "source": "bdb",
      "order": 4,
      "sense": "1"
    },
    {
      "text": "muse",
      "source": "bdb",
      "order": 5,
      "sense": "2"
    },
    {
      "text": "talk",
      "source": "bdb",
      "order": 6,
      "sense": "3a"
    },
    {
      "text": "sing",
      "source": "bdb",
      "order": 7,
      "sense": "3a"
    },
    {
      "text": "talk",
      "source": "bdb",
      "order": 8,
      "sense": "3b"
    },
    {
      "text": "meditate",
      "source": "bdb",
      "order": 9,
      "sense": "0"
    },
    {
      "text": "consider",
      "source": "bdb",
      "order": 10,
      "sense": "0"
    }
  ],
  "sources": {
    "strongs": false,
    "bdb": true
  },
  "occurrences": {
    "total": 4,
    "references": [
      "gen.2.5",
      "gen.21.15",
      "job.30.4",
      "job.30.7"
    ]
  },
  "is_root": false,
  "root_ref": "H7878"
}