[
  {
    "book": "tehilim",
    "book_id": "psalms",
    "book_tth_name": "Tehilim",
    "book_hebrew_name": "תהלים",
    "book_english_name": "Psalms",
    "book_spanish_name": "Salmos",
    "section": "ketuvim",
    "section_hebrew": "כתובים",
    "section_english": "Writings",
    "section_spanish": "Escritos",
    "chapter": 49,
    "verse": 1,
    "status": "present",
    "tth": "¡Escuchen esto todos los pueblos\\!;¡den oído todos los habitantes del mundo\\!,",
    "footnotes": [],
    "hebrew_terms": [],
    "psalm_title": "Para el supervisor. De los hijos de Koraj. Cántico.",
    "psalm_book": 2,
    "book_english_name_lower": "psalms"
  },
  {
    "book": "tehilim",
    "book_id": "psalms",
    "book_tth_name": "Tehilim",
    "book_hebrew_name": "תהלים",
    "book_english_name": "Psalms",
    "book_spanish_name": "Salmos",
    "section": "ketuvim",
    "section_hebrew": "כתובים",
    "section_english": "Writings",
    "section_spanish": "Escritos",
    "chapter": 49,
    "verse": 2,
    "status": "present",
    "tth": "tanto los hijos del hombre como los hijos del varón,juntos, rico y pobre.",
    "footnotes": [],
    "hebrew_terms": [],
    "psalm_title": "Para el supervisor. De los hijos de Koraj. Cántico.",
    "psalm_book": 2,
    "book_english_name_lower": "psalms"
  },
  {
    "book": "tehilim",
    "book_id": "psalms",
    "book_tth_name": "Tehilim",
    "book_hebrew_name": "תהלים",
    "book_english_name": "Psalms",
    "book_spanish_name": "Salmos",
    "section": "ketuvim",
    "section_hebrew": "כתובים",
    "section_english": "Writings",
    "section_spanish": "Escritos",
    "chapter": 49,
    "verse": 3,
    "status": "present",
    "tth": "Mi boca hablará sabiduría,y la meditación de mi corazón, entendimiento.",
    "footnotes": [],
    "hebrew_terms": [],
    "psalm_title": "Para el supervisor. De los hijos de Koraj. Cántico.",
    "psalm_book": 2,
    "book_english_name_lower": "psalms"
  },
  {
    "book": "tehilim",
    "book_id": "psalms",
    "book_tth_name": "Tehilim",
    "book_hebrew_name": "תהלים",
    "book_english_name": "Psalms",
    "book_spanish_name": "Salmos",
    "section": "ketuvim",
    "section_hebrew": "כתובים",
    "section_english": "Writings",
    "section_spanish": "Escritos",
    "chapter": 49,
    "verse": 4,
    "status": "present",
    "tth": "Inclinaré al proverbio mi oído,abriré con el arpa mi enigma.",
    "footnotes": [],
    "hebrew_terms": [],
    "psalm_title": "Para el supervisor. De los hijos de Koraj. Cántico.",
    "psalm_book": 2,
    "book_english_name_lower": "psalms"
  },
  {
    "book": "tehilim",
    "book_id": "psalms",
    "book_tth_name": "Tehilim",
    "book_hebrew_name": "תהלים",
    "book_english_name": "Psalms",
    "book_spanish_name": "Salmos",
    "section": "ketuvim",
    "section_hebrew": "כתובים",
    "section_english": "Writings",
    "section_spanish": "Escritos",
    "chapter": 49,
    "verse": 5,
    "status": "present",
    "tth": "¿Por qué he de temer en días de mal,*cuando la iniquidad de mi suplantador (O, *de mi calcañar*) me rodeará?",
    "footnotes": [],
    "hebrew_terms": [],
    "psalm_title": "Para el supervisor. De los hijos de Koraj. Cántico.",
    "psalm_book": 2,
    "book_english_name_lower": "psalms"
  },
  {
    "book": "tehilim",
    "book_id": "psalms",
    "book_tth_name": "Tehilim",
    "book_hebrew_name": "תהלים",
    "book_english_name": "Psalms",
    "book_spanish_name": "Salmos",
    "section": "ketuvim",
    "section_hebrew": "כתובים",
    "section_english": "Writings",
    "section_spanish": "Escritos",
    "chapter": 49,
    "verse": 6,
    "status": "present",
    "tth": "Los que confían en su fuerzay en la multitud de su riqueza se jactarán;",
    "footnotes": [],
    "hebrew_terms": [],
    "psalm_title": "Para el supervisor. De los hijos de Koraj. Cántico.",
    "psalm_book": 2,
    "book_english_name_lower": "psalms"
  },
  {
    "book": "tehilim",
    "book_id": "psalms",
    "book_tth_name": "Tehilim",
    "book_hebrew_name": "תהלים",
    "book_english_name": "Psalms",
    "book_spanish_name": "Salmos",
    "section": "ketuvim",
    "section_hebrew": "כתובים",
    "section_english": "Writings",
    "section_spanish": "Escritos",
    "chapter": 49,
    "verse": 7,
    "status": "present",
    "tth": "al hermano ciertamente no redimirá el hombre,no dará a Elohim su precio de vida*,",
    "footnotes": [],
    "hebrew_terms": [
      {
        "term": "Elohim",
        "explanation": "Dios, Poderoso"
      }
    ],
    "psalm_title": "Para el supervisor. De los hijos de Koraj. Cántico.",
    "psalm_book": 2,
    "book_english_name_lower": "psalms"
  },
  {
    "book": "tehilim",
    "book_id": "psalms",
    "book_tth_name": "Tehilim",
    "book_hebrew_name": "תהלים",
    "book_english_name": "Psalms",
    "book_spanish_name": "Salmos",
    "section": "ketuvim",
    "section_hebrew": "כתובים",
    "section_english": "Writings",
    "section_spanish": "Escritos",
    "chapter": 49,
    "verse": 8,
    "status": "present",
    "tth": "y costosa es la redención de la vida de ellos,y debe detenerse de intentar para siempre,",
    "footnotes": [],
    "hebrew_terms": [],
    "psalm_title": "Para el supervisor. De los hijos de Koraj. Cántico.",
    "psalm_book": 2,
    "book_english_name_lower": "psalms"
  },
  {
    "book": "tehilim",
    "book_id": "psalms",
    "book_tth_name": "Tehilim",
    "book_hebrew_name": "תהלים",
    "book_english_name": "Psalms",
    "book_spanish_name": "Salmos",
    "section": "ketuvim",
    "section_hebrew": "כתובים",
    "section_english": "Writings",
    "section_spanish": "Escritos",
    "chapter": 49,
    "verse": 9,
    "status": "present",
    "tth": "y vivirá aún para siempre,no verá la destrucción (O, el foso).",
    "footnotes": [],
    "hebrew_terms": [],
    "psalm_title": "Para el supervisor. De los hijos de Koraj. Cántico.",
    "psalm_book": 2,
    "book_english_name_lower": "psalms"
  },
  {
    "book": "tehilim",
    "book_id": "psalms",
    "book_tth_name": "Tehilim",
    "book_hebrew_name": "תהלים",
    "book_english_name": "Psalms",
    "book_spanish_name": "Salmos",
    "section": "ketuvim",
    "section_hebrew": "כתובים",
    "section_english": "Writings",
    "section_spanish": "Escritos",
    "chapter": 49,
    "verse": 10,
    "status": "present",
    "tth": "Porque él ve que los sabios morirán;juntos, el tonto y el estúpido, perecerán,y dejarán a otros su riqueza.",
    "footnotes": [],
    "hebrew_terms": [],
    "psalm_title": "Para el supervisor. De los hijos de Koraj. Cántico.",
    "psalm_book": 2,
    "book_english_name_lower": "psalms"
  },
  {
    "book": "tehilim",
    "book_id": "psalms",
    "book_tth_name": "Tehilim",
    "book_hebrew_name": "תהלים",
    "book_english_name": "Psalms",
    "book_spanish_name": "Salmos",
    "section": "ketuvim",
    "section_hebrew": "כתובים",
    "section_english": "Writings",
    "section_spanish": "Escritos",
    "chapter": 49,
    "verse": 11,
    "status": "present",
    "tth": "*En su interior tienen que sus casas son para siempre (La versión gr. dice: *Su tumba es su casa para siempre*),sus moradas, por generación y generación;llamaron con sus nombres a sus tierras.",
    "footnotes": [],
    "hebrew_terms": [],
    "psalm_title": "Para el supervisor. De los hijos de Koraj. Cántico.",
    "psalm_book": 2,
    "book_english_name_lower": "psalms"
  },
  {
    "book": "tehilim",
    "book_id": "psalms",
    "book_tth_name": "Tehilim",
    "book_hebrew_name": "תהלים",
    "book_english_name": "Psalms",
    "book_spanish_name": "Salmos",
    "section": "ketuvim",
    "section_hebrew": "כתובים",
    "section_english": "Writings",
    "section_spanish": "Escritos",
    "chapter": 49,
    "verse": 12,
    "status": "present",
    "tth": "Mas el hombre, en su honor, no permanecerá;él se compara a los animales que perecen.",
    "footnotes": [],
    "hebrew_terms": [],
    "psalm_title": "Para el supervisor. De los hijos de Koraj. Cántico.",
    "psalm_book": 2,
    "book_english_name_lower": "psalms"
  },
  {
    "book": "tehilim",
    "book_id": "psalms",
    "book_tth_name": "Tehilim",
    "book_hebrew_name": "תהלים",
    "book_english_name": "Psalms",
    "book_spanish_name": "Salmos",
    "section": "ketuvim",
    "section_hebrew": "כתובים",
    "section_english": "Writings",
    "section_spanish": "Escritos",
    "chapter": 49,
    "verse": 13,
    "status": "present",
    "tth": "Este es el camino de ellos, su locura,y los que son después de ellos en sus bocas se complacerán. Selah.",
    "footnotes": [],
    "hebrew_terms": [],
    "psalm_title": "Para el supervisor. De los hijos de Koraj. Cántico.",
    "psalm_book": 2,
    "book_english_name_lower": "psalms"
  },
  {
    "book": "tehilim",
    "book_id": "psalms",
    "book_tth_name": "Tehilim",
    "book_hebrew_name": "תהלים",
    "book_english_name": "Psalms",
    "book_spanish_name": "Salmos",
    "section": "ketuvim",
    "section_hebrew": "כתובים",
    "section_english": "Writings",
    "section_spanish": "Escritos",
    "chapter": 49,
    "verse": 14,
    "status": "present",
    "tth": "Como ovejas para el Sheol fueron puestos,la muerte los pastoreará,y gobernarán sobre ellos los rectos por la mañana;y su forma será para que la consuma el Sheol,desde su habitación.",
    "footnotes": [],
    "hebrew_terms": [],
    "psalm_title": "Para el supervisor. De los hijos de Koraj. Cántico.",
    "psalm_book": 2,
    "book_english_name_lower": "psalms"
  },
  {
    "book": "tehilim",
    "book_id": "psalms",
    "book_tth_name": "Tehilim",
    "book_hebrew_name": "תהלים",
    "book_english_name": "Psalms",
    "book_spanish_name": "Salmos",
    "section": "ketuvim",
    "section_hebrew": "כתובים",
    "section_english": "Writings",
    "section_spanish": "Escritos",
    "chapter": 49,
    "verse": 15,
    "status": "present",
    "tth": "Sin embargo, Elohim redimirá mi serde la mano del Sheol,porque Él me recibirá. Selah.",
    "footnotes": [],
    "hebrew_terms": [
      {
        "term": "Elohim",
        "explanation": "Dios, Poderoso"
      }
    ],
    "psalm_title": "Para el supervisor. De los hijos de Koraj. Cántico.",
    "psalm_book": 2,
    "book_english_name_lower": "psalms"
  },
  {
    "book": "tehilim",
    "book_id": "psalms",
    "book_tth_name": "Tehilim",
    "book_hebrew_name": "תהלים",
    "book_english_name": "Psalms",
    "book_spanish_name": "Salmos",
    "section": "ketuvim",
    "section_hebrew": "כתובים",
    "section_english": "Writings",
    "section_spanish": "Escritos",
    "chapter": 49,
    "verse": 16,
    "status": "present",
    "tth": "No temas cuando se enriquece un hombre,cuando aumenta la gloria de su casa;",
    "footnotes": [],
    "hebrew_terms": [],
    "psalm_title": "Para el supervisor. De los hijos de Koraj. Cántico.",
    "psalm_book": 2,
    "book_english_name_lower": "psalms"
  },
  {
    "book": "tehilim",
    "book_id": "psalms",
    "book_tth_name": "Tehilim",
    "book_hebrew_name": "תהלים",
    "book_english_name": "Psalms",
    "book_spanish_name": "Salmos",
    "section": "ketuvim",
    "section_hebrew": "כתובים",
    "section_english": "Writings",
    "section_spanish": "Escritos",
    "chapter": 49,
    "verse": 17,
    "status": "present",
    "tth": "Porque en su muerte no se llevará nada,no descenderá tras él su gloria.",
    "footnotes": [],
    "hebrew_terms": [],
    "psalm_title": "Para el supervisor. De los hijos de Koraj. Cántico.",
    "psalm_book": 2,
    "book_english_name_lower": "psalms"
  },
  {
    "book": "tehilim",
    "book_id": "psalms",
    "book_tth_name": "Tehilim",
    "book_hebrew_name": "תהלים",
    "book_english_name": "Psalms",
    "book_spanish_name": "Salmos",
    "section": "ketuvim",
    "section_hebrew": "כתובים",
    "section_english": "Writings",
    "section_spanish": "Escritos",
    "chapter": 49,
    "verse": 18,
    "status": "present",
    "tth": "Porque cuando esté vivo bendecirá su ser,y te alabarán cuando te vaya bien;",
    "footnotes": [],
    "hebrew_terms": [],
    "psalm_title": "Para el supervisor. De los hijos de Koraj. Cántico.",
    "psalm_book": 2,
    "book_english_name_lower": "psalms"
  },
  {
    "book": "tehilim",
    "book_id": "psalms",
    "book_tth_name": "Tehilim",
    "book_hebrew_name": "תהלים",
    "book_english_name": "Psalms",
    "book_spanish_name": "Salmos",
    "section": "ketuvim",
    "section_hebrew": "כתובים",
    "section_english": "Writings",
    "section_spanish": "Escritos",
    "chapter": 49,
    "verse": 19,
    "status": "present",
    "tth": "*mas irá hasta la generación de sus padres,jamás (Lit.: hasta siempre no) verán la luz.",
    "footnotes": [],
    "hebrew_terms": [],
    "psalm_title": "Para el supervisor. De los hijos de Koraj. Cántico.",
    "psalm_book": 2,
    "book_english_name_lower": "psalms"
  }
]